Workbook

Sheet Correspondencia AEEH 2026
B1: CORRESPONDENCIA EXTERNA 2026 DIRECCIÓN DE PROYECTOS E INFRAESTRUCTURA ENERGÉTICA
A2: No. | B2: NO. DE TURNO | C2: MES | D2: FECHA DE RECEPCIÓN POR LA DPIE | E2: NO. DE OFICIO | F2: No. EXPEDIENTE | G2: ASUNTO | H2: RESPONSABLE DE DAR ATENCIÓN | I2: NIVEL DE PRIORIDAD | J2: FECHA DE TURNO | K2: ¿SOLICITUD ATENDIDA? | L2: NÚMERO DE GESTIÓN EN SIGA | M2: OFICIO Y/O ACCIÓN DE RESPUESTA | N2: ¿SOLICITUD GESTIONADA ANTE CFE? | O2: GESTIONADA, MEDIANTE OFICIO | P2: ¿CFE DIO RESPUESTA? | Q2: OFICIO CON EL QUE CFE DA RESPUESTA | R2: ¿SOLICITUD GESTIONADA ANTE AYUNTAMIENTOS? | S2: GESTIONADA, MEDIANTE OFICIO | T2: ¿AYUNTAMIENTO DIO RESPUESTA? | U2: OFICIO CON EL QUE EL AYUNTMIENTO DA RESPUESTA | V2: SOLICITUD INGRESADA POR | W2: ÁREA GENERADORA | X2: CLASIFICACIÓN | Y2: MUNICIPIO | Z2: LOCALIDAD | AA2: GÉNERO | AB2: NÚMERO DE TELÉFONO | AC2: CORREO ELECTRÓNICO | AD2: PERSONAS ATENDIDAS | AE2: Beneficiarios Directos | AF2: Beneficiarios Indirectos | AG2: DIVISIONES C F E | AH2: ZONAS CFE | AI2: FIRMA DE RECIBIDO
A3: 1 | B3: 123 | C3: FEBRERO | D3: 46070 | E3: SEDECO/CGI/TI/0156/2026 SDPEE/DGAP/339/2026 | F3: AEEH-2*1S.1/01-2026 ASESORIAS EN MATERIA ENERGÉTICA (VARIOS MUNICIPIOS) | G3: ATENDER AL C. MIGUEL ALONSO HERNÁNDEZ (ANGELICA ALONSO GONZALEZ), PARA CONECTARSE A LA RED DE ENERGÍA ELÉCTRICA EN LA COMUNIDAD DE LAS NUECES, HUEJUTLA (TLANCHINOL) | H3: ING. FRANCISCO | I3: ALTO | J3: 46071 | K3: SI | L3: SDE-UCC-07902-26 | M3: AEEH/DG/152/2026, DE FECHA 23/02/2026, ENVIADO AL ING. OCTAVIO GÓMEZ PAULIN. | N3: SI | O3: AEEH/DG/0731/2026, DE FECHA 03/08/2026, ENVIADO AL ING. HUGO ALEJANDRO ABUNDIS GONZÁLEZ | P3: NO | Q3: N/A | R3: N/A | S3: N/A | T3: N/A | U3: N/A | V3: CIUDADANO (A) | W3: ATENCIÓN AL PUEBLO | X3: 6.- INFRAESTRUCTURA ELÉCTRICA | Y3: 28 HUEJUTLA DE REYES | Z3: LAS NUECES | AA3: MASCULINO | AB3: 7713663097 | AD3: 1 | AE3: =AF3/4 -> 1 | AF3: 4 | AG3: GOLFO CENTRO | AH3: ZONA HUEJUTLA
A4: 2 | B4: 149 | C4: FEBRERO | D4: 46073 | E4: SEDECO /CGI/TI/0190/2026 SDPEE/DGAP/538/2026 | F4: AEEH-2*1S.1/01-2026 ASESORIAS EN MATERIA ENERGÉTICA (VARIOS MUNICIPIOS) | G4: SOLICITA SE LE DE ATENCIÓN AL C. PEDRO MOEDANO BACA, QUIEN SOLICITA INSTALACIÓN DE UNA RED DE ALUMBRADO PÚBLICO | H4: ING. FRANCISCO | I4: ALTO | J4: 46078 | K4: SI | L4: SDE-UCC-07900-26 | M4: AEEH/DG/168/2026, DE FECHA 27/02/2026, ENVIADO AL ING. OCTAVIO GÓMEZ PAULIN. AEEH/DG/193/2026, DE FECHA 09/03/2026, ENVIADO AL ING. OCTAVIO GÓMEZ PAULIN. | N4: NO | O4: N/A | P4: N/A | Q4: N/A | R4: N/A | S4: N/A | T4: N/A | U4: N/A | V4: CIUDADANO (A) | W4: ATENCIÓN AL PUEBLO | X4: 2.- ALUMBRADO PÚBLICO | Y4: 12 ATOTONILCO EL GRANDE | Z4: SAN JOSÉ ZOQUITAL | AA4: MASCULINO | AB4: 7712067240 | AC4: gutierrezolguinm@gmail.com | AD4: 1 | AE4: =AF4/4 -> 425 | AF4: 1700 | AG4: CENTRO ORIENTE | AH4: ZONA PACHUCA
A5: 3 | B5: 225 | C5: MARZO | D5: 46092 | E5: SEDECO/CGI/TI/0297/2026 SDPEE/DGAP/1048/2026 | F5: AEEH-2*1S.1/01-2026 ASESORIAS EN MATERIA ENERGÉTICA (VARIOS MUNICIPIOS) | G5: ATENDER A LA C. TANIA SULEMA CALVA HERRERA, QUIEN SOLICITA LA AMPLIACION DE RED ELECTRICA EN SU COMUNIDAD | H5: ING. FRANCISCO | I5: ALTO | J5: 46094 | K5: SI | L5: SDE-UC-00117-26 | M5: AEEH/DG/238/2026, DE FECHA 23/03/2026, ENVIADO AL ING. OCTAVIO GÓMEZ PAULIN. AEEH/DG/278/2026, DE FECHA 31/03/2026, ENVIADO AL ING. OCTAVIO GÓMEZ PAULIN. | N5: NO | O5: N/A | P5: N/A | Q5: N/A | R5: N/A | S5: N/A | T5: N/A | U5: N/A | V5: CIUDADANO (A) | W5: ATENCIÓN AL PUEBLO | X5: 3.- ELECTRIFICACIÓN | Y5: 9 EL ARENAL | Z5: OJO DE AGUA | AA5: FEMENINO | AB5: 7714057898 | AD5: 1 | AE5: 1 | AF5: 0 | AG5: CENTRO ORIENTE | AH5: ZONA PACHUCA
A6: 4 | B6: 291 | C6: ABRIL | D6: 46119 | E6: SEDECO/CGI/TI/0408/2026 SDPEE/DGAP/1816/2026 | F6: AEEH-2*1S.1/01-2026 ASESORIAS EN MATERIA ENERGÉTICA (VARIOS MUNICIPIOS) | G6: ATENDER A LA DELEGADA GRICELDA MARTÍNEZ CHÁVEZ, QUIEN SOLICITA APOYO PARA CAMBIAR LA LINEA DE LUZ YA QUE LOS POSTES SE ENCUENTRAN EN MAL ESTADO | H6: ING. FRANCISCO | I6: ALTO | J6: 46119 | K6: SI | L6: SDE-UC-00316-26 | M6: AEEH/DG/311/2026, DE FECHA 10/04/2026, ENVIADO AL ING. OCTAVIO GÓMEZ PAULIN COORDINADOR DE GESTIÓN INSTITUCIONAL | N6: SI | O6: AEEH/DG/386/2026, DE FECHA 28/04/2026, ENVIADO AL ING. ALEJANDRO YUSULMAN HERNÁNDEZ LEAL, SUPERINTENDENTE DE CFE DISTRIBUCIÓN ZONA IXMIQUILPAN | P6: NO | Q6: N/A | R6: N/A | S6: N/A | T6: N/A | U6: N/A | V6: DELEGADO (A) MUNICIPAL | W6: ATENCIÓN AL PUEBLO | X6: 8.- MEJORAS A LA RED | Y6: 6 ALFAJAYUCAN | Z6: BOXTHÓ | AA6: FEMENINO | AB6: 7721374560 | AD6: 1 | AE6: =AF6/4 -> 30 | AF6: 120 | AG6: DIVISION BAJIO | AH6: ZONA IXMIQUILPAN
A7: 5 | B7: 068 | C7: FEBRERO | D7: 46057 | E7: S/N | F7: AEEH-2*1S.5/01-2026 ENERGIA REGIONAL | G7: ENERGIA REGIONAL SOLICITA AUDIENCIA PARA PRESENTAR LA PROPUESTA "ESTUDIO TÉCNICO JUSTIFICATIVO PARA LA INSCRIPCIÓN DE PROYECTOS DE ELECTRICIDAD EN LA PLANEACIÓN VINCULANTE" | H7: ARQ. ORLANDO | I7: ALTO | J7: 46057 | K7: SI | L7: SDE-UCC-07705-26 | M7: AEEH/DG/319/2026, DE FECHA 10/04/2026, ENVIADO AL ING. OCTAVIO GOMEZ PAULIN, COORDINADOR DE GESTÍON INSTITUCIONAL ARQ. ORLANDO SE CONECTA A LA REUNIÓN CON EL C. MIGUEL ÁNGEL HORTA MARTIN | N7: N/A | O7: N/A | P7: N/A | Q7: N/A | R7: N/A | S7: N/A | T7: N/A | U7: N/A | V7: EMPRESA PRIVADA | W7: OTRAS INSTANCIAS | X7: 7.- INVITACIONES/EXPOS/CONGRESOS/TEMAS ADMINISTRATIVOS/CAPACITACIONES/ATENCIÓN A EMPRESAS/ELECTROMOVILIDAD/OTROS | AA7: MASCULINO | AB7: 55 41 77 30 76 | AC7: miguel.horta@eregional.com.mx | AD7: 1 | AE7: 1 | AF7: 0 | AG7: N/A | AH7: N/A
A8: 6 | B8: 316 | C8: ABRIL | D8: 46125 | E8: SEDECO/CGI/TI/0450/2026 SDPEE/DGAP/2191/2026 | F8: AEEH-2*1S.1/01-2026 ASESORIAS EN MATERIA ENERGÉTICA (VARIOS MUNICIPIOS) | G8: ATENDER A PEDRO GUERRERO GONZALEZ, QUIEN SOLICITA LA AMPLIACIÓN DE LA RED DE ENERGIA ELECTRICA Y COLOCACIÓN DE 2 TRANSFORMADORES EN SU LOCALIDAD | H8: ING. FRANCISCO | I8: ALTO | J8: 46125 | K8: SI | L8: SDE-UC-00404-26 | M8: AEEH/DG/359/2026, DE FECHA 21/04/2026, ENVIADO AL ING. OCTAVIO GOMEZ PAULIN | N8: SI | O8: AEEH/DG/432/2026, DE FECHA 14/05/2026, ENVIADO AL ING. ALEJANDRO YUSULMAN HERNÁNDEZ LEAL, SUPERINTENDENTE DE LA CFE ZONA IXMIQUILPAN | P8: NO | Q8: N/A | R8: N/A | S8: N/A | T8: N/A | U8: N/A | V8: DELEGADO (A) MUNICIPAL | W8: ATENCIÓN AL PUEBLO | X8: 3.- ELECTRIFICACIÓN | Y8: 29 HUICHAPAN | Z8: JONACOPA | AA8: MASCULINO | AB8: 7731284313 | AC8: pedroguerrerogonz30@gmail.com | AD8: 1 | AE8: =AF8/4 -> 45 | AF8: 180 | AG8: DIVISION BAJIO | AH8: ZONA IXMIQUILPAN
A9: 7 | B9: 509 | C9: JUNIO | D9: 46190 | E9: SEDECO/CGI/TI/0758/2026 SDPEE/DGAP/3882/2026 | F9: AEEH-2*1S.1/01-2026 ASESORIAS EN MATERIA ENERGÉTICA (VARIOS MUNICIPIOS) | G9: ATENDER AL C. ROGELIO MORALES HERNÁNDEZ, QUIEN SOLICITA MEDIACIÓN CON CFE PARA LA REUBICACIÓN DE UN POSTE DE SU LOCALIDAD. | H9: ING. FRANCISCO | I9: ALTO | J9: 46191 | K9: SI | L9: SDE-UC-01014-26 | M9: AEEH/DG/590/2026, DE FECHA 30/06/2026, ENVIADO AL ING. OCTAVIO GÓMEZ PAULIN, COORDINADOR DE GESTIÓN INSTITUCIONAL. | N9: NO | O9: N/A | P9: N/A | Q9: N/A | V9: DELEGADO (A) MUNICIPAL | W9: ATENCIÓN AL PUEBLO | X9: 13.- REUBICACIÓN DE POSTES | Y9: 81 ZACUALTIPÁN DE ÁNGELES | Z9: SAN MIGUEL FERRERÍA | AA9: MASCULINO | AB9: 55 45 33 81 78 | AD9: 1 | AG9: GOLFO CENTRO | AH9: ZONA HUEJUTLA
A10: 8 | B10: 510 | C10: JUNIO | D10: 46190 | E10: SEDECO/CGI/TI/0759/2026 SDPEE/DGAP/3883/2026 | F10: AEEH-2*1S.1/01-2026 ASESORIAS EN MATERIA ENERGÉTICA (VARIOS MUNICIPIOS) | G10: ATENDER AL C. ROGELIO MORALES HERNÁNDEZ, QUIEN SOLICITA MEDIACIÓN CON CFE PARA LA REHABILITACIÓN DE ALUMBRADO PÚBLICO. | H10: ING. FRANCISCO | I10: ALTO | J10: 46191 | K10: SI | L10: SDE-UC-00993-26 | M10: AEEH/DG/591/2026, DE FECHA 30/06/2026, ENVIADO AL ING. OCTAVIO GÓMEZ PAULIN, COORDINADOR DE GESTIÓN INSTITUCIONAL. | N10: N/A | O10: N/A | P10: N/A | Q10: N/A | V10: DELEGADO (A) MUNICIPAL | W10: ATENCIÓN AL PUEBLO | X10: 2.- ALUMBRADO PÚBLICO | Y10: 81 ZACUALTIPÁN DE ÁNGELES | Z10: SAN MIGUEL FERRERÍA | AA10: MASCULINO | AB10: 55 45 33 81 78 | AD10: 1 | AG10: GOLFO CENTRO | AH10: ZONA HUEJUTLA
A11: 9 | B11: 511 | C11: JUNIO | D11: 46190 | E11: SEDECO/CGI/TI/0760/2026 SDPEE/DGAP/3962/2026 | F11: AEEH-2*1S.1/01-2026 ASESORIAS EN MATERIA ENERGÉTICA (VARIOS MUNICIPIOS) | G11: ATENDER A MARÍA CRISTINA PÉREZ HERNÁNDEZ, QUIEN SOLICITA MEDIACIÓN CON CFE, ANTE MULTA IMPUESTA POR CANCELACIÓN DE SERVICIO. | H11: ARQ. DIEGO | I11: ALTO | J11: 46191 | K11: SI | L11: SDE-UC-01018-26 | M11: AEEH/DG/592/2026, DE FECHA 30/06/2026, ENVIADO AL ING. OCTAVIO GÓMEZ PAULIN, COORDINADOR DE GESTIÓN INSTITUCIONAL. | N11: N/A | O11: N/A | P11: N/A | Q11: N/A | V11: CIUDADANO (A) | W11: ATENCIÓN AL PUEBLO | X11: 1.- ADEUDO | Y11: 38 MINERAL DEL CHICO | Z11: CAPULA | AA11: FEMENINO | AB11: 771 760 3516 | AD11: 1 | AG11: CENTRO ORIENTE | AH11: ZONA PACHUCA
A12: 10 | B12: 516 | C12: JUNIO | D12: 46190 | E12: SEDECO/CGI/TI/0761/2026 SDPEE/DGAP/3937/2026 | F12: AEEH-2*1S.1/01-2026 ASESORIAS EN MATERIA ENERGÉTICA (VARIOS MUNICIPIOS) | G12: ATENDER A FIDENCIA SIERRA PEREZ, QUIEN SOLICITA LA INTRODUCCIÓN DEL SERVICIO DE ENERGÍA ELÉCTRICA | H12: ING. FRANCISCO | I12: ALTO | J12: 46191 | K12: SI | L12: SDE-UC-01016-26 | M12: AEEH/DG/593/2026, DE FECHA 30/06/2026, ENVIADO AL ING. OCTAVIO GÓMEZ PAULIN, COORDINADOR DE GESTIÓN INSTITUCIONAL. | N12: N/A | O12: N/A | P12: N/A | Q12: N/A | V12: CIUDADANO (A) | W12: ATENCIÓN AL PUEBLO | X12: 3.- ELECTRIFICACIÓN | Y12: 56 SANTIAGO TULANTEPEC DE LUGO GUERRERO | Z12: ALTEPEMILA | AA12: FEMENINO | AB12: 775 260 0224 | AD12: 1 | AG12: CENTRO ORIENTE | AH12: ZONA TULANCINGO
A13: 11 | B13: 512 | C13: JUNIO | D13: 46190 | E13: SEDECO/CGI/TI/0762/2026 SDPEE/DGAP/3991/2026 | F13: AEEH-2*1S.1/01-2026 ASESORIAS EN MATERIA ENERGÉTICA (VARIOS MUNICIPIOS) | G13: ATENDER A RICARDO GRANADOS MEDINA, QUIEN SOLICITA APOYO PARA INSTALACIÓN DE ALUMBRADO PÚBLICO EN SU FRACCIONMIENTO | H13: ING. FRANCISCO | I13: ALTO | J13: 46191 | K13: SI | L13: SDE-UC-01017-26 | M13: AEEH/DG/594/2026, DE FECHA 30/06/2026, ENVIADO AL ING. OCTAVIO GÓMEZ PAULIN, COORDINADOR DE GESTIÓN INSTITUCIONAL. | N13: N/A | O13: N/A | P13: N/A | Q13: N/A | V13: CIUDADANO (A) | W13: ATENCIÓN AL PUEBLO | X13: 2.- ALUMBRADO PÚBLICO | Y13: 51 MINERAL DE LA REFORMA | Z13: PRADERAS DE VIRREYES | AA13: MASCULINO | AB13: 55 45 90 0874 | AD13: 1 | AG13: CENTRO ORIENTE | AH13: ZONA PACHUCA
A14: 12 | B14: 513 | C14: JUNIO | D14: 46190 | E14: SEDECO/CGI/TI/0763/2026 SDPEE/DGAP/3993/2026 | F14: AEEH-2*1S.1/01-2026 ASESORIAS EN MATERIA ENERGÉTICA (VARIOS MUNICIPIOS) | G14: ATENDER A JOSE SIERRA CASTELÁN, QUIEN SOLICITA LA AMPLIACIÓN DE RED ELECTRICA EN SU COMUNIDAD | H14: ING. FRANCISCO | I14: ALTO | J14: 46191 | K14: SI | L14: SDE-UC-01019-26 | M14: AEEH/DG/595/2026, DE FECHA 30/06/2026, ENVIADO AL ING. OCTAVIO GÓMEZ PAULIN, COORDINADOR DE GESTIÓN INSTITUCIONAL. | N14: N/A | O14: N/A | P14: N/A | Q14: N/A | V14: CIUDADANO (A) | W14: ATENCIÓN AL PUEBLO | X14: 3.- ELECTRIFICACIÓN | Y14: 56 SANTIAGO TULANTEPEC DE LUGO GUERRERO | Z14: COL. LOS ROMEROS | AA14: MASCULINO | AB14: 55 12 44 77 85 | AD14: 1 | AG14: CENTRO ORIENTE | AH14: ZONA TULANCINGO
A15: 13 | B15: 514 | C15: JUNIO | D15: 46190 | E15: SEDECO/CGI/TI/0764/2026 SDPEE/DGAP/3998/2026 | F15: AEEH-2*1S.1/01-2026 ASESORIAS EN MATERIA ENERGÉTICA (VARIOS MUNICIPIOS) | G15: ATENDER A LA C. EVA JAZMIN GONZÁLEZ GONZÁLEZ, QUIEN SOLICITA EL SERVICIO DE ENERGÍA ELÉCTRICA PARA 30 VIVIENDAS DE SU LOCALIDAD | H15: ING. FRANCISCO | I15: ALTO | J15: 46191 | K15: SI | L15: SDE-UC-01020-26 | M15: AEEH/DG/596/2026, DE FECHA 30/06/2026, ENVIADO AL ING. OCTAVIO GÓMEZ PAULIN, COORDINADOR DE GESTIÓN INSTITUCIONAL. | N15: N/A | O15: N/A | P15: N/A | Q15: N/A | V15: CIUDADANO (A) | W15: ATENCIÓN AL PUEBLO | X15: 3.- ELECTRIFICACIÓN | Y15: 56 SANTIAGO TULANTEPEC DE LUGO GUERRERO | Z15: SAN FRANCISCO HUATENGO | AA15: FEMENINO | AB15: 775 235 8855 | AD15: 1 | AG15: CENTRO ORIENTE | AH15: ZONA TULANCINGO
A16: 14 | B16: 515 | C16: JUNIO | D16: 46190 | E16: SEDECO/CGI/TI/0765/2026 SDPEE/DGAP/4000/2026 | F16: AEEH-2*1S.1/01-2026 ASESORIAS EN MATERIA ENERGÉTICA (VARIOS MUNICIPIOS) | G16: ATENDER A LA C. MARÍA DEL CARMEN RIVERA MARTÍNEZ, QUIEN SOLICITA LA AMPLIACIÓN DE RED DE ENERGÍA ELECTRICA EN SU LOCALIDAD | H16: ING. FRANCISCO | I16: ALTO | J16: 46191 | K16: SI | L16: SDE-UC-01021-26 | M16: AEEH/DG/597/2026, DE FECHA 30/06/2026, ENVIADO AL ING. OCTAVIO GÓMEZ PAULIN, COORDINADOR DE GESTIÓN INSTITUCIONAL. | N16: N/A | O16: N/A | P16: N/A | Q16: N/A | V16: CIUDADANO (A) | W16: ATENCIÓN AL PUEBLO | X16: 3.- ELECTRIFICACIÓN | Y16: 16 CUAUTEPEC DE HINOJOSA | Z16: TEPANTITLA | AA16: FEMENINO | AB16: 775 141 6197 | AD16: 1 | AG16: CENTRO ORIENTE | AH16: ZONA TULANCINGO
A17: 15 | B17: 386 | C17: MAYO | D17: 46149 | E17: SEDECO/CGI/0158/2026 | F17: AEEH-2*1S/08-2026 SOLICITUDES DE LA DIRECCIÓN DE ATENCIÓN AL PUEBLO | G17: INVITACIÓN PARA ASISTIR A REUNIONES TRIMETRALES CON LA DIRECCIÓN DE ATENCIÓN AL PUEBLO | H17: ARQ. ORLANDO | I17: BAJO | J17: 46149 | K17: SI | L17: SDE-CGI-00265-26 | M17: DE CONOCIMIENTO | N17: N/A | O17: N/A | P17: N/A | Q17: N/A | R17: N/A | S17: N/A | T17: N/A | U17: N/A | V17: DEPENDENCIA ESTATAL | W17: OTRAS INSTANCIAS | X17: 7.- INVITACIONES/EXPOS/CONGRESOS/TEMAS ADMINISTRATIVOS/CAPACITACIONES/ATENCIÓN A EMPRESAS/ELECTROMOVILIDAD/OTROS | AD17: 1 | AE17: 1 | AF17: 0 | AG17: N/A | AH17: N/A
A18: 16 | B18: 021 | C18: ENERO | D18: 46043 | E18: SEDECO/CGI/0013/2026 | F18: AEEH-2*1S/08-2026 SOLICITUDES DE LA DIRECCIÓN DE ATENCIÓN AL PUEBLO | G18: DESIGNAR UN ENLACE PARA EL SEGUIMIENTO Y RESOLUCIÓN DE LAS SOLICITUDES DE LA DIRECCIÓN DE ATENCIÓN AL PUEBLO | H18: LIC. ARELI | I18: BAJO | J18: 46043 | K18: SI | L18: SDE-CGI-00202-26 | M18: AEEH/DG/052/2026, DE FECHA 23/01/2026, ENVIADO AL ING. OCTAVIO GÓMEZ PAULIN, COORDINADOR DE GESTIÓN INSTITUCIONAL | N18: N/A | O18: N/A | P18: N/A | Q18: N/A | R18: N/A | S18: N/A | T18: N/A | U18: N/A | V18: DEPENDENCIA ESTATAL | W18: OTRAS INSTANCIAS | X18: 7.- INVITACIONES/EXPOS/CONGRESOS/TEMAS ADMINISTRATIVOS/CAPACITACIONES/ATENCIÓN A EMPRESAS/ELECTROMOVILIDAD/OTROS | AA18: MASCULINO | AB18: 771 688 6026 | AC18: octavio.gomez@hidalgo.gob.mx | AD18: 1 | AE18: 1 | AF18: 0 | AG18: N/A | AH18: N/A
A19: 17 | B19: 039 | C19: ENERO | D19: 46042 | E19: UPLAPH/COEMERE/013/2026 | F19: AEEH-2*1S/04-2026 MEJORA REGULATORIA | G19: LA COEMERE SOLICITA ELABORAR LA ACTUALIZACIÓN DEL CIERRE DEL PROGRAMA ANUAL DE MEJORA REGULATORIA 2025 EN LA PLATAFORMA AID-RUTS | H19: LIC. ARELI ING. FRANCISCO | I19: ALTO | J19: 46043 | K19: SI | L19: N/A | M19: AEEH/DG/055/2026, DE FECHA 26/01/2026, ENVIADO AL MTRO. ANDRÉS MANNING NOVALES, TITULAR DE LA COEMERE | N19: N/A | O19: N/A | P19: N/A | Q19: N/A | R19: N/A | S19: N/A | T19: N/A | U19: N/A | V19: DEPENDENCIA ESTATAL | W19: OTRAS INSTANCIAS | X19: 7.- INVITACIONES/EXPOS/CONGRESOS/TEMAS ADMINISTRATIVOS/CAPACITACIONES/ATENCIÓN A EMPRESAS/ELECTROMOVILIDAD/OTROS | AA19: MASCULINO | AB19: 771 715 6672 | AC19: dependencias.coemere@hidalgo.gob.mx | AD19: 1 | AE19: 1 | AF19: 0 | AG19: N/A | AH19: N/A
A20: 18 | B20: 562 | C20: JULIO | D20: 46211 | E20: CENACE/DOPS/354/2026 | F20: SANDY | G20: CENACE EMITE INVITACIÓN A PARTICIPAR EN REUNIONES DEL PROCESO DE ELABORACIÓN DEL PRONÓSTICO DE DEMANDA Y CONSUMO DE ENERGÍA ELECTRICA 2027 - 2041 | H20: ING. SANDRA | I20: ALTO | J20: 46211 | K20: SI | L20: SDE-AEEH-00406-26 | M20: AEEH/DG/0650/2026, DE FECHA 09/07/2026, ENVIADO AL ING. MAURICIO CUÉLLAR AHUMADA, SUBGERENTE DE OPERACIÓN Y DESPACHO DE LA GERENCIA DEL CENTRO NACIONAL Y ENCARGADO DE LA DIRECCIPON DE OPERACIÓN Y PLANEACIÓN DEL SISTEMA. AEEH/DG/0651/2026, DE FECHA 09/07/2026, ENVIADO AL ING. CINTHYA YARELY MEZA CORTÉS, DIRECTORA GENERAL DE LA AGENCIA DE DESARROLLO VALLE DE PLATA, DIO RESPUESTA CON TURNO 586 Y OFICIO ADVP/330/2026. AEEH/DG/0653/2026, DE FECHA 09/07/2026, ENVIADO AL MTRO. ERNESTO CADENA ACOSTA, SUBSECRETARIO DE INVERSIONES Y ECONOMÍA SECTORIAL, DIO RESPUESTA CON TURNO 587 Y OFICIO SEDECO/SIyES/109/2026. | N20: N/A | O20: N/A | P20: N/A | Q20: N/A | R20: N/A | S20: N/A | T20: N/A | U20: N/A | V20: DEPENDENCIA FEDERAL | W20: OTRAS INSTANCIAS | X20: 7.- INVITACIONES/EXPOS/CONGRESOS/TEMAS ADMINISTRATIVOS/CAPACITACIONES/ATENCIÓN A EMPRESAS/ELECTROMOVILIDAD/OTROS | AD20: 1 | AE20: 1 | AF20: 0 | AG20: N/A | AH20: N/A
A21: 19 | B21: 089 | C21: FEBRERO | D21: 46057 | E21: UPLAPH/COEMERE/105/2026 | F21: AEEH-2*1S/04-2026 MEJORA REGULATORIA | G21: DESIGNACIÓN O RATIFICACIÓN DE LOS ENLACES ANTE LA COMISIÓN DE MEJORA REGULATORIA | H21: LIC. ARELI | I21: ALTO | J21: 46057 | K21: SI | L21: N/A | M21: AEEH/DG/077/2026, DE FECHA 05/02/2026, ENVIADO AL MTRO. ANDRÉS MANNING NOVALES AEEH/DG/085-1/2026, DE FECHA 06/02/2026, ENVIADO A ARQ. ORLANDO MARTÍNEZ JUÁREZ AEEH/DG/085-2/2026, DE FECHA 06/02/2026, ENVIADO A ING. FRANCISCO JAVIER GARCÍA VILLALPA AEEH/DG/085-3/2026, DE FECHA 06/02/2026, ENVIADO A LIC. EVA BERENICE RAMÍREZ PÉREZ AEEH/DG/085-4/2026, DE FECHA 06/02/2026, ENVIADO A LIC. CARLOS LÓPEZ ESPINOSA | N21: N/A | O21: N/A | P21: N/A | Q21: N/A | R21: N/A | S21: N/A | T21: N/A | U21: N/A | V21: DEPENDENCIA ESTATAL | W21: OTRAS INSTANCIAS | X21: 7.- INVITACIONES/EXPOS/CONGRESOS/TEMAS ADMINISTRATIVOS/CAPACITACIONES/ATENCIÓN A EMPRESAS/ELECTROMOVILIDAD/OTROS | AA21: MASCULINO | AB21: 771 715 6672 | AC21: dependencias.coemere@hidalgo.gob.mx | AD21: 1 | AE21: 1 | AF21: 0 | AG21: N/A | AH21: N/A
A22: 20 | B22: 624 | C22: JULIO | D22: 46232 | E22: UPLAPH/COEMERE/236/2026 | G22: LA COMISIÓN ESTATAL DE MEJORA REGULATORIA SOLICITA REQUISITAR EL FORMATO CORRESPONDIENTE AL CENSO NACIONAL DE GOBIERNOS ESTATALES 2026, COORDINADO POR EL INEGI, EN LO REFERENTE A TRÁMITES Y SERVICIOS DE LA AGENCIA | H22: ARQ. ORLANDO LIC. ARELI | I22: ALTO | J22: 46232 | K22: SI | L22: N/A | M22: AEEH/DG/0773/2026, DE FECHA 10/08/2026, ENVIADO AL MTRO. ANDRÉS MANNING NOVALES, TITULAR DE LA COEMERE | N22: N/A | O22: N/A | P22: N/A | Q22: N/A | R22: N/A | S22: N/A | T22: N/A | U22: N/A | V22: DEPENDENCIA ESTATAL | W22: OTRAS INSTANCIAS | X22: 7.- INVITACIONES/EXPOS/CONGRESOS/TEMAS ADMINISTRATIVOS/CAPACITACIONES/ATENCIÓN A EMPRESAS/ELECTROMOVILIDAD/OTROS | AD22: 1 | AG22: N/A | AH22: N/A
A23: 21 | B23: 662 | C23: AGOSTO | D23: 46244 | E23: SEMARNATH/DESP/SSyCC/DGCC/000386/2026 | F23: AEEH-2*1S.4/07-2026 PROGRAMA ESTATAL DE ACCIÓN ANTE EL CAMBIO CLIMATICO DE HIDALGO / COMISIÓN ESTATAL INTERSECTORIAL DEL CAMBIO CLIMATICO | G23: INVITACIÓN A REUNIÓN VIRTUAL EL 12 DE AGOSTO PARA LA VALIDACIÓN DE FICHAS DEL PROGRAMA ESTATAL DE ACCIÓN ANTE EL CAMBIO CLIMATICO DEL ESTADO DE HIDALGO (PEACCH) | H23: ARQ. DIEGO | I23: MEDIO | J23: 46244 | K23: SI | L23: SDE-AEEH-00425-26 | M23: AEEH/DG/0781/2026, DE FECHA 13/08/2026, ENVIADO A LA MTRA. MONICA PATRICIA MIXTEGA TREJO, SECRETARIA DE LA SEMARNATH | N23: N/A | O23: N/A | P23: N/A | Q23: N/A | R23: N/A | S23: N/A | T23: N/A | U23: N/A | V23: DEPENDENCIA ESTATAL | W23: OTRAS INSTANCIAS | X23: 7.- INVITACIONES/EXPOS/CONGRESOS/TEMAS ADMINISTRATIVOS/CAPACITACIONES/ATENCIÓN A EMPRESAS/ELECTROMOVILIDAD/OTROS | AA23: FEMENINO | AD23: 1 | AE23: 1 | AG23: N/A | AH23: N/A
A24: 22 | B24: 658 | C24: AGOSTO | D24: 46245 | E24: SEDECO/CGI/TI/0983/2026 SDPEE/DGAP/5398/2026 | F24: DIEGO | G24: ATENDER A MARTINIANO MARTÍNEZ BAUTISTA, QUIEN SOLICITA LA AMPLIACIÓN DE LA RED DE ENERGÍA ELECTRICA (4 POSTES) | H24: ARQ. DIEGO | I24: ALTO | J24: 46245 | K24: SI | L24: SDE-UC-01506-26 | M24: AEEH/DG/0795/2026, DE FECHA 12/08/2026, ENVIADO AL ING. OCTAVIO GÓMEZ PAULIN, COORDINADOR DE GESTIÓN INSTITUCIONAL | N24: SI | O24: AEEH/DG/0832/2026, DE FECHA 18/08/2026, ENVIADO AL ING. HUGO ALEJANDRO ABUNDIS GONZALEZ, SUPERINTENDENTE DE LA COMISIÓN FEDERAL DE LECTRICIDAD ZONA HUEJUTLA | P24: N/A | Q24: N/A | V24: CIUDADANO (A) | W24: ATENCIÓN AL PUEBLO | X24: 3.- ELECTRIFICACIÓN | Y24: 14 CALNALI | AA24: MASCULINO | AD24: 1 | AE24: 1 | AG24: GOLFO CENTRO | AH24: ZONA HUEJUTLA
A25: 23 | B25: 668 | C25: AGOSTO | D25: 46245 | E25: SEDECO/CGI/TI/0992/2026 SDPEE/DGAP/5460/2026 | F25: DIEGO | G25: ATENDER A ESTANISLAO OCAÑA PEREZ, QUIEN SOLICITA APOYO PARA LA ATENCIÓN A PROBLEMÁTICA TERRITORIAL QUE IMPIDE LA AMPLIACIÓN DE RED ELECTRICA. | H25: ARQ. DIEGO | I25: ALTO | J25: 46245 | K25: SI | L25: SDE-UC-01523-26 | M25: AEEH/DG/0796/2026, DE FECHA 12/08/2026, ENVIADO AL ING. OCTAVIO GÓMEZ PAULIN, COORDINADOR DE GESTIÓN INSTITUCIONAL | N25: N/A | O25: N/A | P25: N/A | Q25: N/A | V25: CIUDADANO (A) | W25: ATENCIÓN AL PUEBLO | X25: 3.- ELECTRIFICACIÓN | Y25: 30 IXMIQUILPAN | Z25: CERRO BLANCO | AA25: MASCULINO | AD25: 1 | AE25: 1 | AG25: DIVISION BAJIO | AH25: ZONA IXMIQUILPAN
A26: 24 | B26: 023 | C26: ENERO | D26: 46045 | E26: SDG/DGAP/119/2026 SEDECO/CGI/TI/0028/2026 | F26: AEEH-2*1S.1/01-2026 ASESORIAS EN MATERIA ENERGÉTICA (VARIOS MUNICIPIOS) | G26: SOLICITA SE LE DE ATENCIÓN AL C. EDUARDO MONTES CUELLAR , QUIEN SOLICITA APOYO PARA DAR CONTINUIDAD A LA AMPLIACIÓN DE RED ELÉCTRICA DE SU CALLE | H26: ING. FRANCISCO | I26: MEDIO | J26: 46048 | K26: SI | L26: SDE-UCC-07558-26 | M26: AEEH/DG/080/2026, DE FECHA 05/02/2026, ENVIADO AL ING. OCTAVIO GÓMEZ PAULIN, COORDINADOR DE GESTIÓN INSTITUCIONAL CERRADA | N26: NO | O26: N/A | P26: N/A | Q26: N/A | R26: N/A | S26: N/A | T26: N/A | U26: N/A | V26: CIUDADANO (A) | W26: ATENCIÓN AL PUEBLO | X26: 3.- ELECTRIFICACIÓN | Y26: 58 TASQUILLO | Z26: LA NUEZ | AA26: MASCULINO | AB26: 772 119 5254 | AD26: 1 | AE26: =AF26/4 -> 26 | AF26: 104 | AG26: DIVISION BAJIO | AH26: ZONA IXMIQUILPAN
A27: 25 | B27: 635 | C27: AGOSTO | D27: 46238 | E27: SEDECO/SIyES/TI/104/2026 | F27: DIEGO | G27: SUBSECRETARIA DE INVERSIONES Y ECONOMIA SECTORIAL, SOLICITA REVISIÓN DE UGAS DE LA INDUSTRIA ENERGETICA, PARA DAR CUMPLIMIENTO AL PROGRAMA DE ORDENAMIENTO ECOLOGICO LOCAL PARTICIPATIVO( POELP) PACHUCA DE SOTO | H27: ARQ. DIEGO | I27: ALTO | J27: 46232 | K27: SI | L27: SDE-SIES-00347-26 | M27: AEEH/DG/0805/2026, DE FECHA 14/08/2026, ENVIADO AL ARQ. ERNESTO CADENA ACOSTA SUBSECRETARIO DE INVERSIONES Y ECONOMÍA SECTORIAL DE LA SECRETARÍA DE DESARROLLO ECONÓMICO (SEDECO) NO SE CARGO EN SIGA PORQUE VENCIÓ EL PERIODO, SE ENVÍO POR CORREO ELECTRÓNICO Y SE ENTREGO EN LA SUBSECRETARIA | N27: N/A | O27: N/A | P27: N/A | Q27: N/A | R27: N/A | S27: N/A | T27: N/A | U27: N/A | V27: DEPENDENCIA ESTATAL | W27: OTRAS INSTANCIAS | X27: 7.- INVITACIONES/EXPOS/CONGRESOS/TEMAS ADMINISTRATIVOS/CAPACITACIONES/ATENCIÓN A EMPRESAS/ELECTROMOVILIDAD/OTROS | AD27: 1 | AE27: 1 | AG27: N/A | AH27: N/A
A28: 26 | B28: 620 | C28: AGOSTO | D28: 46238 | E28: SEDECO/CGI/TI/0936/2026 SDPEE/DGAP/5123/2026 | F28: SANDRA | G28: ATENDER A FRANCISCO ZARATE HERNANDEZ, SOLICITA INTERVENCION CON CFE PARA LA AMPLIACION DE RED DE ENERGIA ELECTRICA EN SU LOCALIDAD. | H28: ING. SANDRA | I28: ALTO | J28: 46232 | K28: SI | L28: SDE-UC-01401-26 | M28: AEEH/DG/0809/2026, DE FECHA 14/08/2026, ENVIADO AL ING. OCTAVIO GOMEZ PAULIN, COORDINADOR DE GESTIÓN INSTICUCIONAL | N28: SI | O28: AEEH/DG/0826/2026, DE FECHA 18/08/2026, ENVIADO AL ING. HUGO ALEJANDRO ABUNDIS GONZALEZ, SUPERINTENDENTE DE LA COMISIÓN FEDERAL DE LECTRICIDAD ZONA HUEJUTLA | P28: N/A | Q28: N/A | V28: CIUDADANO (A) | W28: ATENCIÓN AL PUEBLO | X28: 3.- ELECTRIFICACIÓN | Y28: 25 HUAUTLA | Z28: ACATEPEC | AA28: MASCULINO | AD28: 1 | AE28: 1 | AG28: GOLFO CENTRO | AH28: ZONA HUEJUTLA
A29: 27 | B29: 616 | C29: AGOSTO | D29: 46238 | E29: SEDECO/CGI/TI/0930/2026 SDPEE/DGAP/5066/2026 | F29: SANDRA | G29: ATENDER A LIZBET MARILU RESENDIZ OSORIO, SOLICITA LA INTRODUCCIÓN DE ENERGIA ELECTRICA QUE BENEFICIARA A 37 VECINOS DE LA LOCALIDAD. | H29: ING. SANDRA | I29: ALTO | J29: 46232 | K29: SI | L29: SDE-UC-01377-26 | M29: AEEH/DG/0810/2026, DE FECHA 14/08/2026, ENVIADO AL ING. OCTAVIO GOMEZ PAULIN, COORDINADOR DE GESTIÓN INSTITUCIONAL. AEEH/DPIE/077/2026, DE FECHA 24/08/2026, ENVIADO A LA MAP. MARIA GUADALUPE OLGUÍN ROMERO, DIRECTORA DE ACCIONES SOCIALES PARA LA JUSTICIA ENERGÉTICA. | N29: SI | O29: AEEH/DG/0824/2026, DE FECHA 18/08/2026, ENVIADO AL ING. JOSE LUIS FRANCISCO CRAVIOTO, SUPERINTENDENTE GENERAL E.F. DE LA COMISIÓN FEDERAL DE LECTRICIDAD ZONA IXMIQUILPNA | P29: N/A | Q29: N/A | V29: CIUDADANO (A) | W29: ATENCIÓN AL PUEBLO | X29: 3.- ELECTRIFICACIÓN | Y29: 18 CHAPULHUACÁN | Z29: EL CHINILLAR | AA29: FEMENINO | AD29: 1 | AE29: 1 | AG29: DIVISION BAJIO | AH29: ZONA IXMIQUILPAN
A30: 28 | B30: 615 | C30: AGOSTO | D30: 46238 | E30: SEDECO/CGI/TI/0929/2026 SDPEE/DGAP/5044/2026 | F30: SANDRA | G30: ATENDER A FLAVIO HERNANDEZ HERNANDEZ, SOLICITA SERVICIO DE ENERGIA ELECTRICA EN SU LOCALIDAD | H30: ING. SANDRA | I30: ALTO | J30: 46232 | K30: SI | L30: SDE-UC-01369-26 | M30: AEEH/DG/0811/2026, DE FECHA 14/08/2026, ENVIADO AL ING. OCTAVIO GOMEZ PAULIN, COORDINADOR DE GESTIÓN INSTITUCIONAL. AEEH/DPIE/076/2026, DE FECHA 20/08/2026, ENVIADO A LA MAP. MARIA GUADALUPE OLGUÍN ROMERO, DIRECTORA DE ACCIONES SOCIALES PARA LA JUSTICIA ENERGÉTICA. | N30: SI | O30: AEEH/DG/0823/2026, DE FECHA 18/08/2026, ENVIADO AL ING. JOSE LUIS FRANCISCO CRAVIOTO, SUPERINTENDENTE GENERAL E.F. DE LA COMISIÓN FEDERAL DE LECTRICIDAD ZONA IXMIQUILPAN | P30: N/A | Q30: N/A | V30: CIUDADANO (A) | W30: ATENCIÓN AL PUEBLO | X30: 3.- ELECTRIFICACIÓN | Y30: 18 CHAPULHUACÁN | Z30: PUERTO DEL TAMBOR | AA30: MASCULINO | AD30: 1 | AE30: 1 | AG30: DIVISION BAJIO | AH30: ZONA IXMIQUILPAN
A31: 29 | B31: 619 | C31: AGOSTO | D31: 46238 | E31: SEDECO/CGI/TI/0935/2026 SDPEE/DGAP/5101/2026 | F31: SANDRA | G31: ATENDER A FRANCISCO ZARATE HERNANDEZ, SOLICITA ALUMBRADO PUBLICO EN CALLES CERCANAS AL CENTRO DE SALUD | H31: ING. SANDRA | I31: ALTO | J31: 46232 | K31: SI | L31: SDE-UC-01399-26 | M31: AEEH/DG/0812/2026, DE FECHA 14/08/2026, ENVIADO AL ING. OCTAVIO GOMEZ PAULIN, COORDINADOR DE GESTIÓN INSTITUCIONAL | N31: N/A | O31: N/A | P31: N/A | Q31: N/A | R31: SI | S31: AEEH/DG/0861/2026, DE FECHA 24/08/2026, ENVIADO AL ING. JORGE ALBERTO HERNANDEZ CORTÉS, PRESIDENTE MUNICIPAL DE HUAUTLA | V31: CIUDADANO (A) | W31: ATENCIÓN AL PUEBLO | X31: 2.- ALUMBRADO PÚBLICO | Y31: 25 HUAUTLA | Z31: ACATEPEC | AA31: MASCULINO | AD31: 1 | AE31: 1 | AG31: GOLFO CENTRO | AH31: ZONA HUEJUTLA
A32: 30 | B32: 656 | C32: AGOSTO | D32: 46245 | E32: SEDECO/CGI/TI/0981/2026 SDPEE/DGAP/5385/2026 | F32: SANDY | G32: ATENDER A DIANA SANCHEZ RODRIGUEZ, SOLICITA APOYO CON EL REACOMODO DE LOS CABLES DE LUZ QUE SE ENCUENTRAN CERCA DE SU DOMICILIO. | H32: ING. SANDRA | I32: ALTO | J32: 46245 | K32: SI | L32: SDE-UC-01508-26 | M32: AEEH/DG/0813/2026, DE FECHA 14/08/2026, ENVIADO AL ING. OCTAVIO GOMEZ PAULIN, COORDINADOR DE GESTIÓN INSTICUCIONAL | N32: SI | O32: AEEH/DG/0825/2026, DE FECHA 18/08/2026, ENVIADO AL ING. HUGO ALEJANDRO ABUNDIS GONZALEZ, SUPERINTENDENTE DE LA COMISIÓN FEDERAL DE LECTRICIDAD ZONA HUEJUTLA | P32: N/A | Q32: N/A | V32: CIUDADANO (A) | W32: ATENCIÓN AL PUEBLO | X32: 8.- MEJORAS A LA RED | Y32: 14 CALNALI | Z32: PEZMATLAN | AA32: FEMENINO | AD32: 1 | AE32: 1 | AG32: GOLFO CENTRO | AH32: ZONA HUEJUTLA
A33: 31 | B33: 657 | C33: AGOSTO | D33: 46245 | E33: SEDECO/CGI/TI/0982/2026 SDPEE/DGAP/5392/2026 | F33: SANDY | G33: ATENDER A ANTONIO HERNÁNDEZ HERNÁNDEZ, QUIEN SOLICITA LA AMPLIACIÓN DE RED DE ENERGÍA ELECTRICA (10 POSTES DE ENERGÍA) | H33: ING. SANDRA | I33: ALTO | J33: 46245 | K33: SI | L33: SDE-UC-01501-26 | M33: AEEH/DG/0814/2026, DE FECHA 14/08/2026, ENVIADO AL ING. OCTAVIO GOMEZ PAULIN, COORDINADOR DE GESTIÓN INSTICUCIONAL | N33: SI | O33: AEEH/DG/0827/2026, DE FECHA 18/08/2026, ENVIADO AL ING. HUGO ALEJANDRO ABUNDIS GONZALEZ, SUPERINTENDENTE DE LA COMISIÓN FEDERAL DE LECTRICIDAD ZONA HUEJUTLA | P33: N/A | Q33: N/A | V33: CIUDADANO (A) | W33: ATENCIÓN AL PUEBLO | X33: 3.- ELECTRIFICACIÓN | Y33: 73 TLANCHINOL | Z33: TOTONICAPA | AA33: MASCULINO | AD33: 1 | AE33: 1 | AG33: GOLFO CENTRO | AH33: ZONA HUEJUTLA
A34: 32 | B34: 672 | C34: AGOSTO | D34: 46246 | E34: SEDECO/CGI/TI/0999/2026 SDPEE/DGAP/5541/2026 | F34: SANDY | G34: ATENDER A ARTURO FELIX ACOSTA, SOLICITA LA INSTALACIÓN DE LAMPARAS SOLARES O CELDAS FOTOVOLTAICOS PARA ALUMBRADO DE ÁREAS RECREATIVAS DE SU LOCALIDAD | H34: ING. SANDRA | I34: ALTO | J34: 46246 | K34: SI | L34: SDE-UC-01528-26 | M34: AEEH/DG/0815/2026, DE FECHA 12/08/2026, ENVIADO AL ING. OCTAVIO GÓMEZ PAULIN, COORDINADOR DE GESTIÓN INSTITUCIONAL | N34: N/A | O34: N/A | P34: N/A | Q34: N/A | X34: 2.- ALUMBRADO PÚBLICO | Y34: 14 CALNALI | Z34: COYULA | AG34: GOLFO CENTRO | AH34: ZONA HUEJUTLA
A35: 33 | B35: 673 | C35: AGOSTO | D35: 46246 | E35: SEDECO/CGI/TI/1002/2026 SDPEE/DGAP/5570/2026 | F35: SANDY | G35: ATENDER A WILEVALDO NAJERA TORRES, QUIEN SOLICITA LA INTERVENCIÓN CON CFE TRAS UN AJUSTE DE FACTURACIÓN (MULTA POR $66,523.00) | H35: ING. SANDRA | I35: ALTO | J35: 46246 | K35: SI | L35: SDE-UC-01529-26 | M35: AEEH/DG/0816/2026, DE FECHA 14/08/2026, ENVIADO AL ING. OCTAVIO GÓMEZ PAULIN, COORDINADOR DE GESTIÓN INSTITUCIONAL | N35: SI | O35: AEEH/DG/0830/2026, DE FECHA 18/08/2026, ENVIADO AL ING. RAFAEL NAVARRO PÉREZ, SUPERINTENDENTE DE LA COMISIÓN FEDERAL DE LECTRICIDAD ZONA PACHUCA | P35: SI | Q35: RNP-335-2026 | R35: N/A | S35: N/A | T35: N/A | U35: N/A | X35: 1.- ADEUDO | Y35: 52 SAN AGUSTÍN TLAXIACA
A36: 34 | B36: 697 | C36: AGOSTO | D36: 46253 | E36: SEDECO/CGI/TI/1032/2026 SDPEE/DGAP/5763/2026 | F36: DIEGO | G36: ATENDER A FILIBERTO HILARIO MOEDANO, QUIEN SOLICITA ALUMBRADO PÚBLICO EN SU LOCALIDAD | H36: ARQ. DIEGO | I36: ALTO | J36: 46254 | K36: SI | L36: SDE-UC-01596-26 | M36: AEEH/DG/0845/2026, DE FECHA 20/08/2026, ENVIADO AL ING. OCTAVIO GÓMEZ PAULIN, COORDINADOR DE GESTIÓN INSTITUCIONAL | N36: N/A | O36: N/A | P36: N/A | Q36: N/A | R36: N/A | S36: N/A | T36: N/A | U36: N/A | V36: CIUDADANO (A) | W36: ATENCIÓN AL PUEBLO | X36: 2.- ALUMBRADO PÚBLICO | Y36: 81 ZACUALTIPÁN DE ÁNGELES | AA36: MASCULINO | AD36: 1 | AG36: GOLFO CENTRO | AH36: ZONA HUEJUTLA
A37: 35 | B37: 696 | C37: AGOSTO | D37: 46253 | E37: SEDECO/CGI/TI/1033/2026 SDPEE/DGAP/5697/2026 | F37: DIEGO | G37: ATENDER A JUAN LOPEZ TELLEZ, QUIEN SOLICITA LA MODERNIZACIÓN Y REUBICACIÓN DE LA RED ELECTRICA DE SU LOCALIDAD | H37: ARQ. DIEGO | I37: ALTO | J37: 46254 | K37: SI | L37: SDE-UC-01593-26 | M37: AEEH/DG/0850/2026, DE FECHA 21/08/2026, ENVIADO AL ING. OCTAVIO GÓMEZ PAULIN, COORDINADOR DE GESTIÓN INSTITUCIONAL | N37: N/A | O37: N/A | P37: N/A | Q37: N/A | R37: N/A | S37: N/A | T37: N/A | U37: N/A | V37: CIUDADANO (A) | W37: ATENCIÓN AL PUEBLO | X37: 8.- MEJORAS A LA RED | Y37: 37 METZTITLÁN | AA37: FEMENINO | AD37: 1 | AG37: GOLFO CENTRO | AH37: ZONA HUEJUTLA
A38: 36 | B38: 693 | C38: AGOSTO | D38: 46253 | E38: SEDECO/CGI/TI/1029/2026 SDPEE/DGAP/5713/2026 | F38: DIEGO | G38: ATENDER A ARACELI CORTES SONI, QUIEN SOLICITA ALUMBRADO PÚBLICO PARA SU LOCALIDAD. | H38: ARQ. DIEGO | I38: ALTO | J38: 46254 | K38: SI | L38: SDE-UC-01594-26 | M38: AEEH/DG/0851/2026, DE FECHA 21/08/2026, ENVIADO AL ING. OCTAVIO GÓMEZ PAULIN, COORDINADOR DE GESTIÓN INSTITUCIONAL | N38: N/A | O38: N/A | P38: N/A | Q38: N/A | R38: N/A | S38: N/A | T38: N/A | U38: N/A | V38: CIUDADANO (A) | W38: ATENCIÓN AL PUEBLO | X38: 2.- ALUMBRADO PÚBLICO | Y38: 79 XOCHICOATLÁN | AA38: FEMENINO | AD38: 1 | AG38: GOLFO CENTRO | AH38: ZONA HUEJUTLA
A39: 37 | B39: 687 | C39: AGOSTO | D39: 46253 | E39: SEDECO/CGI/TI/1015/2026 SDPEE/DGAP/5602/2026 | F39: SANDY | G39: ATENDER A JOSE FELIPE JIMÉNEZ VIVEROS, QUIEN SOLICITA LA REUBICACIÓN DE UN POSTE EL CUAL ES PELIGROSO PARA LOS HABITANTES DE SU DOMICILIO. | H39: ING. SANDRA | I39: ALTO | J39: 46254 | K39: SI | L39: SDE-UC-01551-26 | M39: AEEH/DG/0856/2026, DE FECHA 24/08/2026, ENVIADO AL ING. OCTAVIO GÓMEZ PAULIN, COORDINADOR DE GESTIÓN INSTITUCIONAL | N39: N/A | O39: N/A | P39: N/A | Q39: N/A | R39: N/A | S39: N/A | T39: N/A | U39: N/A | V39: CIUDADANO (A) | W39: ATENCIÓN AL PUEBLO | X39: 13.- REUBICACIÓN DE POSTES | Y39: 48 PACHUCA DE SOTO | AA39: MASCULINO | AD39: 1 | AG39: CENTRO ORIENTE | AH39: ZONA PACHUCA
A40: 38 | B40: 694 | C40: AGOSTO | D40: 46253 | E40: SEDECO/CGI/TI/1030/2026 SDPEE/DGAP/5721/2026 | F40: SANDY | G40: ATENDER A VIRGINIA BAÑOS ISLAS, QUIEN SOLICITA MEDIACIÓN CON CFE POR UN PRESUNTO ADEUDO. | H40: ING. SANDRA | I40: ALTO | J40: 46254 | K40: SI | L40: SDE-UC-01591-26 | M40: AEEH/DG/0857/2026, DE FECHA 24/08/2026, ENVIADO AL ING. OCTAVIO GÓMEZ PAULIN, COORDINADOR DE GESTIÓN INSTITUCIONAL | N40: N/A | O40: N/A | P40: N/A | Q40: N/A | R40: N/A | S40: N/A | T40: N/A | U40: N/A | V40: CIUDADANO (A) | W40: ATENCIÓN AL PUEBLO | X40: 1.- ADEUDO | Y40: 48 PACHUCA DE SOTO | AA40: FEMENINO | AD40: 1 | AG40: CENTRO ORIENTE | AH40: ZONA PACHUCA
A41: 39 | B41: 695 | C41: AGOSTO | D41: 46253 | E41: SEDECO/CGI/TI/1034/2026 SDPEE/DGAP/5780/2026 | F41: SANDY | G41: ATENDER A JUANA FRANCISCO BELIO, QUIEN SOLICITA ALUMBRADO PÚBLICO PARA SU LOCALIDAD | H41: ING. SANDRA | I41: ALTO | J41: 46254 | K41: SI | L41: SDE-UC-01590-26 | M41: AEEH/DG/0858/2026, DE FECHA 24/08/2026, ENVIADO AL ING. OCTAVIO GÓMEZ PAULIN, COORDINADOR DE GESTIÓN INSTITUCIONAL | N41: N/A | O41: N/A | P41: N/A | Q41: N/A | R41: SI | S41: AEEH/DG/0864/2026, DE FECHA 24/08/2026, ENVIADO AL PROFR. LUIS ENRIQUE TAPIA ZAPATA, PRESIDENTE MUNICIPAL CONSTITUCIONAL DE JUAREZ, HIDALGO. | V41: CIUDADANO (A) | W41: ATENCIÓN AL PUEBLO | X41: 2.- ALUMBRADO PÚBLICO | Y41: 33 JUÁREZ HIDALGO | Z41: SAN NICOLAS COATZONTLA | AA41: FEMENINO | AD41: 1 | AG41: GOLFO CENTRO | AH41: ZONA HUEJUTLA
A42: 40 | B42: 698 | C42: AGOSTO | D42: 46253 | E42: SEDECO/CGI/TI/1031/2026 SDPEE/DGAP/5736/2026 | F42: SANDY | G42: ATENDER A LEONCIO ALVAREZ ALARCON, QUIEN SOLICITA APOYO PARA LA CORRECIÓN DE DATOS EN RECIBOS DE LUZ | H42: ARQ. ORLANDO ING. SANDRA | I42: ALTO | J42: 46254 | K42: SI | L42: SDE-UC-01595-26 | M42: AEEH/DG/0859/2026, DE FECHA 24/08/2026, ENVIADO AL ING. OCTAVIO GÓMEZ PAULIN, COORDINADOR DE GESTIÓN INSTITUCIONAL | N42: SI | O42: AEEH/DG/0862/2026, DE FECHA 24/08/2026, ENVIADO AL ING. HUGO ALEJANDRO ABUNDIS GONZALEZ, SUPERINTENDENTE DE LA COMISIÓN FEDERAL DE LECTRICIDAD ZONA HUEJUTLA | P42: N/A | Q42: N/A | R42: N/A | S42: N/A | T42: N/A | U42: N/A | V42: CIUDADANO (A) | W42: ATENCIÓN AL PUEBLO | X42: 14.- CONCILIACIÓN ANTE CFE | Y42: 68 TIANGUISTENGO | AA42: MASCULINO | AD42: 1 | AG42: GOLFO CENTRO | AH42: ZONA HUEJUTLA
A43: 41 | B43: 718 | C43: AGOSTO | D43: 46261 | E43: SEDECO/CGI/TI/1074/2026 SDPEE/DGAP/6034/2026 | F43: SANDY | G43: ATENDER A ANTONIO MONTIEL ESCAMILLA, QUIEN SOLICITA APOYO PARA LA AMPLIACIÓN DE ENERGÍA ELECTRICA EN SU LOCALIDAD. | H43: ING. SANDRA | I43: ALTO | J43: 46261 | K43: SI | L43: SDE-UC-01682-26 | M43: AEEH/DG/0874/2026, DE FECHA 28/08/2026, ENVIADO AL ING. OCTAVIO GÓMEZ PAULIN, COORDINADOR DE GESTIÓN INSTITUCIONAL | N43: SI | O43: AEEH/DG/0890/2026, DE FECHA 01/09/2026, ENVIADO AL ING. HUGO ALEJANDRO ABUNDIS GONZALEZ, SUPERINTENDENTE DE LA COMISIÓN FEDERAL DE LECTRICIDAD ZONA HUEJUTLA | V43: CIUDADANO (A) | W43: ATENCIÓN AL PUEBLO | X43: 8.- MEJORAS A LA RED | Y43: 37 METZTITLÁN | Z43: BARRIO LOS CERRITOS | AD43: 1 | AG43: GOLFO CENTRO | AH43: ZONA HUEJUTLA
A44: 42 | B44: 706 | C44: AGOSTO | D44: 46260 | E44: SEDECO/CGI/TI/1063/2026 SDPEE/DGAP/5929/2026 | F44: SANDY | G44: ATENDER A ALICIA GOMEZ ZAPATA, QUIEN SOLICITA AMPLIACIÓN DE LUZ ELECTRICA (NO CUENTAN CON EL SERVICIO) | H44: ING. SANDRA | I44: ALTO | J44: 46260 | K44: SI | L44: SDE-UC-01644-26 | M44: AEEH/DG/0875/2026, DE FECHA 28/08/2026, ENVIADO AL ING. OCTAVIO GÓMEZ PAULIN, COORDINADOR DE GESTIÓN INSTITUCIONAL | N44: SI | O44: AEEH/DG/0891/2026, DE FECHA 01/09/2026, ENVIADO AL ING. HUGO ALEJANDRO ABUNDIS GONZALEZ, SUPERINTENDENTE DE LA COMISIÓN FEDERAL DE LECTRICIDAD ZONA HUEJUTLA | P44: N/A | Q44: N/A | R44: N/A | S44: N/A | T44: N/A | U44: N/A | V44: CIUDADANO (A) | W44: ATENCIÓN AL PUEBLO | X44: 8.- MEJORAS A LA RED | Y44: 71 TLAHUILTEPA | Z44: AGUA DEL CUERVO | AA44: FEMENINO | AD44: 1 | AG44: GOLFO CENTRO | AH44: ZONA HUEJUTLA
A45: 43 | B45: 690 | C45: AGOSTO | D45: 46260 | E45: SEMARNATH/DESP/DGOET/410-2026 | F45: DIEGO | G45: SEMARNATH SOLICITA INFORMACION DE LOS PLANES, PROGRAMAS Y PROYECTOS EN LOS MUNICIPIOS DE SAN GUSTÍN TLAXIACA, TLAHUELILPAN, TEPETILAN, TEZONTEPEC DE ALDAMA Y TULA DE ALLENDE | H45: ARQ. DIEGO | I45: ALTO | J45: 46260 | K45: SI | L45: SDE-AEEH-00432-26 | M45: AEEH/DG/0881/2026, DE FECHA 31/08/2026, ENVIADO A LA MTRA. MÓNICA PATRICIA MIXTEGA TREJO, SECRETARIA DE MEDIO AMBIENTE Y RECURSOS NATURALES DEL ESTADO DE HIDALGO | N45: N/A | O45: N/A | P45: N/A | Q45: N/A | R45: N/A | S45: N/A | T45: N/A | U45: N/A | V45: DEPENDENCIA ESTATAL | W45: OTRAS INSTANCIAS | X45: 7.- INVITACIONES/EXPOS/CONGRESOS/TEMAS ADMINISTRATIVOS/CAPACITACIONES/ATENCIÓN A EMPRESAS/ELECTROMOVILIDAD/OTROS | AD45: 1 | AG45: N/A | AH45: N/A
A46: 44 | B46: 707 | C46: AGOSTO | D46: 46260 | E46: SEDECO/CGI/TI/1062/2026 SDPEE/DGAP/5917/2026 | F46: DIEGO | G46: ATENDER A CLEMENTE CORREA ACOSTA, QUIEN SOLICITA INTERVENCIÓN CON CFE PARA CAMBIAR LA RUTA DE LA RED ELECTRICA DE SU LOCALIDAD. | H46: ARQ. DIEGO | I46: ALTO | J46: 46260 | K46: SI | L46: SDE-UC-01638-26 | M46: AEEH/DG/0883/2026, DE FECHA 31/08/2026, ENVIADO AL ING. OCTAVIO GÓMEZ PAULIN, COORDINADOR DE GESTIÓN INSTITUCIONAL | N46: N/A | O46: N/A | P46: N/A | Q46: N/A | R46: N/A | S46: N/A | T46: N/A | U46: N/A | V46: CIUDADANO (A) | W46: ATENCIÓN AL PUEBLO | X46: 8.- MEJORAS A LA RED | Y46: 71 TLAHUILTEPA | Z46: LAZARO CARDENAS | AD46: 1 | AG46: CENTRO ORIENTE | AH46: ZONA TULA
A47: 45 | B47: 022 | C47: ENERO | D47: 46045 | E47: SDG/DGAP/113/2026 SEDECO/CGI/TI/0027/2026 | F47: AEEH-2*1S.1/01-2026 ASESORIAS EN MATERIA ENERGÉTICA (VARIOS MUNICIPIOS) | G47: SOLICITA ATENDER A LA C. ANASTACIA MARTÍNEZ CORDERO, QUIEN SOLICITA APOYO PARA REUBICAR UN POSTE DE LUZ UBICADO DENTRO DE LA ESCUELA PRIMARIA "BENITO JUAREZ" | H47: ING. FRANCISCO | I47: MEDIO | J47: 46048 | K47: SI | L47: SDE-UCC-07557-26 | M47: AEEH/DG/092/2026, DE FECHA 09/02/2026, ENVIADO AL ING. OCTAVIO GÓMEZ PAULIN, COORDINADOR DE GESTIÓN INSTITUCIONAL | N47: SI | O47: AEEH/DG/083/2026, DE FECHA 06/02/2026, ENVIADO AL ING. ALEJANDRO YUSULMAN HERNÁNDEZ LEAL DE CFE | P47: NO | Q47: N/A | R47: N/A | S47: N/A | T47: N/A | U47: N/A | V47: CIUDADANO (A) | W47: ATENCIÓN AL PUEBLO | X47: 8.- MEJORAS A LA RED | Y47: 47 PACULA | Z47: JILIAPAN | AA47: FEMENINO | AB47: 772 117 4762 | AC47: anamaco_10yahoo.com.mx | AD47: 1 | AE47: =AF47/4 -> 150 | AF47: 600 | AG47: DIVISION BAJIO | AH47: ZONA IXMIQUILPAN
A48: 46 | B48: 090 | C48: FEBRERO | D48: 46059 | E48: SDPEE/DGAP/163/2026 SEDECO/CGI/TI/0121/2026 | F48: AEEH-2*1S.1/01-2026 ASESORIAS EN MATERIA ENERGÉTICA (VARIOS MUNICIPIOS) | G48: ATEN DER AL C. DAVID RAMIREZ VALENCIA, QUIEN SOLICITA APOYO CON LA INSTALACIÓN DE ALUMBRADO PÚBLICO | H48: ING. FRANCISCO | I48: ALTO | J48: 46059 | K48: SI | L48: SDE-UCC-07744-26 | M48: AEEH/DG/093/2026, DE FECHA 09/02/2026, ENVIADO AL ING. OCTAVIO GÓMEZ PAULIN. AEEH/DG/143/2026, DE FECHA 18/02/2026, ENVIADO AL ING. OCTAVIO GÓMEZ PAULIN. | N48: NO | O48: N/A | P48: N/A | Q48: N/A | R48: SI | S48: OFICIO AEEH/DG/154/2026, DE FECHA 23/02/2026, ENVIADO A LA C. ABRIL MARTÍNEZ PORTILLO, PRESIDENTA MUNICIPAL DE TLANALAPA | T48: NO | U48: N/A | V48: CIUDADANO (A) | W48: ATENCIÓN AL PUEBLO | X48: 2.- ALUMBRADO PÚBLICO | Y48: 72 TLANALAPA | Z48: TLANALAPA | AA48: MASCULINO | AB48: 771 112 2551 | AC48: davidramval7@gmail.com | AD48: 1 | AE48: =AF48/4 -> 71 | AF48: 284 | AG48: CENTRO ORIENTE | AH48: ZONA TULANCINGO
A49: 47 | B49: 103 | C49: FEBRERO | D49: 46059 | E49: SDPEE/DGAP/213/2026 SEDECO/CGI/TI/0124/2026 | F49: AEEH-2*1S.1/01-2026 ASESORIAS EN MATERIA ENERGÉTICA (VARIOS MUNICIPIOS) | G49: ATENDER A LA C. MARÍA DE JESÚS VILLEGAS CERVANTES, PARA BENEFICIARLA CON ALUMBRADO PÚBLICO | H49: ING. FRANCISCO | I49: ALTO | J49: 46059 | K49: SI | L49: SDE-UCC-07772-26 | M49: AEEH/DG/094/2026, DE FECHA 09/02/2026, ENVIADO AL ING. OCTAVIO GÓMEZ PAULIN. AEEH/DG/144/2026, DE FECHA 18/02/2026, ENVIADO AL ING. OCTAVIO GÓMEZ PAULIN. | N49: N/A | O49: N/A | P49: N/A | Q49: N/A | R49: SI | S49: AEEH/DG/160/2026, DE FECHA 25/02/2026, ENVIADO AL MTRO. FRANCISCO SINUHÉ REMÍREZ OVIEDO, PRESIDENTE MUNICIPAL DE ZEMPOALA | T49: NO | U49: N/A | V49: CIUDADANO (A) | W49: ATENCIÓN AL PUEBLO | X49: 2.- ALUMBRADO PÚBLICO | Y49: 83 ZEMPOALA | Z49: SAN JUAN TEPERNAZALCO | AA49: FEMENINO | AB49: 561 161 3676 | AC49: villegascervantes120973@gmail.com | AD49: 1 | AE49: =AF49/4 -> 2 | AF49: 8 | AG49: CENTRO ORIENTE | AH49: ZONA PACHUCA
A50: 48 | B50: 130 | C50: FEBRERO | D50: 46072 | E50: OM/0225-14/2026 | F50: AEEH-2*1S/05-2026 SOLICITUDES DE PRACTICAS, SERVICIO SOCIAL Y RESIDENCIA | G50: DESIGNACIÓN DE ENLACE INSTITUCIONAL DEL PROGRAMA DE SERVICIO SOCIAL Y PRÁCTICAS PROFESIONALES ANTE OFICILÍA MAYOR | H50: LIC. ARELI | I50: MEDIO | J50: 46072 | K50: SI | L50: N/A | M50: AEEH/DG/132/2026, DE FECHA 16/02/2026, ENVIADO A LA MTRA. JESSICA ESPERANZA GONZALEZ DÍAZ SE DESIGNA A ARELI HERNÁNDEZ COMO ENLACE Y ASISTE A LA CAPACITACIÓN EN PALACIO DE GOBIERNO. | N50: N/A | O50: N/A | P50: N/A | Q50: N/A | R50: N/A | S50: N/A | T50: N/A | U50: N/A | V50: DEPENDENCIA ESTATAL | W50: OTRAS INSTANCIAS | X50: 7.- INVITACIONES/EXPOS/CONGRESOS/TEMAS ADMINISTRATIVOS/CAPACITACIONES/ATENCIÓN A EMPRESAS/ELECTROMOVILIDAD/OTROS | AA50: MASCULINO | AB50: 771 717 6000 Ext. 6283 | AD50: 1 | AE50: 1 | AF50: 0 | AG50: N/A | AH50: N/A
A51: 49 | B51: 128 | C51: FEBRERO | D51: 46070 | E51: IHDM/DG/021/2026 | F51: AEEH-2*1S.3/05-2026 INSTITUTO HIDALGUENSE PARA EL DESARROLLO MUNICIPAL | G51: EL INSTITUTO HIDALGUENSE PARA EL DESARROLLO MUNICIPAL, SOLICITA LA DESIGNACIÓN DE ENLACE PARA APOYAR Y ACERCAR HERRAMIENTAS A LOS GOBIERNOS MUNICIPALES | H51: ARQ. ORLANDO | I51: MEDIO | J51: 46064 | K51: SI | L51: N/A | M51: AEEH/DG/141/2026, DE FECHA 18/02/2026, ENVIADO VIA CORREO ELECTRONICO AL LIC. ABEL CERÓN SAN NICOLÁS, DIRECTOR GENERAL DEL IHDM | N51: N/A | O51: N/A | P51: N/A | Q51: N/A | R51: N/A | S51: N/A | T51: N/A | U51: N/A | V51: DEPENDENCIA ESTATAL | W51: OTRAS INSTANCIAS | X51: 7.- INVITACIONES/EXPOS/CONGRESOS/TEMAS ADMINISTRATIVOS/CAPACITACIONES/ATENCIÓN A EMPRESAS/ELECTROMOVILIDAD/OTROS | Z51: COL. CENTRO | AA51: MASCULINO | AB51: 771 718 8904 | AC51: abel.ceron@hidalgo.gob.mx ihdm@hidalgo.gob.mx | AD51: 1 | AE51: 1 | AF51: 0 | AG51: N/A | AH51: N/A
A52: 50 | B52: 116 | C52: FEBRERO | D52: 46064 | E52: SDPEE/DGAP/234/2026 SEDECO/CGI/TI/0124/2026 | F52: AEEH-2*1S.1/01-2026 ASESORIAS EN MATERIA ENERGÉTICA (VARIOS MUNICIPIOS) | G52: SOLICITA ATENDER AL C. JUAN GUZMÁN EVARISTO, QUIEN SOLICITA APOYO PARA LA ADQUISICIÓN DE PANELES SOLARES PARA BALNEARIO DE SU COMUNIDAD | H52: ING. FRANCISCO | I52: ALTO | J52: 46064 | K52: SI | L52: SDE-UCC-07785-26 | M52: AEEH/DG/145/2026, DE FECHA 18/02/2026, ENVIADO AL ING. OCTAVIO GÓMEZ PAULIN. AEEH/DG/153/2026, DE FECHA 23/02/2026, ENVIADO AL ING. OCTAVIO GÓMEZ PAULIN. | N52: N/A | O52: N/A | P52: N/A | Q52: N/A | R52: N/A | S52: N/A | T52: N/A | U52: N/A | V52: CIUDADANO (A) | W52: ATENCIÓN AL PUEBLO | X52: 4.- ENERGÍA RENOVABLE (SOLAR, EÓLICA) | Y52: 73 TLANCHINOL | Z52: SANTA MARÍA | AA52: MASCULINO | AB52: 771 203 8521 | AC52: jorgedana178@gmail.com | AD52: 1 | AE52: =AF52/4 -> 1 | AF52: 4 | AG52: GOLFO CENTRO | AH52: ZONA HUEJUTLA
A53: 51 | B53: 150 | C53: FEBRERO | D53: 46073 | E53: SEDECO /CGI/TI/0191/2026 SDPEE/DGAP/539/2026 | F53: AEEH-2*1S.1/01-2026 ASESORIAS EN MATERIA ENERGÉTICA (VARIOS MUNICIPIOS) | G53: SOLICITA SE LE DE ATENCIÓN A LA C. JUANA ELIZARRAGA VÁZQUEZ, QUIEN SOLICITA APOYO PARA LA AMPLIACIÓN O CONTINUIDAD DE LUZ CON POSTES FALTANTES | H53: ING. FRANCISCO | I53: ALTO | J53: 46078 | K53: SI | L53: SDE-UCC-07901-26 | M53: AEEH/DG/169/2026, DE FECHA 27/02/2026, ENVIADO AL ING. OCTAVIO GÓMEZ PAULIN. | N53: NO | O53: N/A | P53: N/A | Q53: N/A | R53: N/A | S53: N/A | T53: N/A | U53: N/A | V53: CIUDADANO (A) | W53: ATENCIÓN AL PUEBLO | X53: 3.- ELECTRIFICACIÓN | Y53: 12 ATOTONILCO EL GRANDE | Z53: EL NOVILLERO | AA53: FEMENINO | AB53: 7712387661 | AD53: 1 | AE53: 10 | AF53: 39 | AG53: CENTRO ORIENTE | AH53: ZONA PACHUCA
A54: 52 | B54: 151 | C54: FEBRERO | D54: 46073 | E54: SEDECO /CGI/TI/0192/2026 SDPEE/DGAP/540/2026 | F54: AEEH-2*1S.1/01-2026 ASESORIAS EN MATERIA ENERGÉTICA (VARIOS MUNICIPIOS) | G54: SOLICITA SE LE DE ATENCIÓN AL C. ERNESTO SOTO CASTAÑEDA, QUIEN SOLICITA APOYO PARA LA REPARACIÓN DE LAS LAMPARAS DE SU COMUNIDAD ASÍ COMO POSTES EN MAL ESTADO. | H54: ING. FRANCISCO | I54: ALTO | J54: 46078 | K54: SI | L54: SDE-UCC-07899-26 | M54: AEEH/DG/170/2026, DE FECHA 27/02/2026, ENVIADO AL ING. OCTAVIO GÓMEZ PAULIN. AEEH/DG/194/2026, DE FECHA 09/03/2026, ENVIADO AL ING. OCTAVIO GÓMEZ PAULIN. | N54: NO | O54: N/A | P54: N/A | Q54: N/A | R54: N/A | S54: N/A | T54: N/A | U54: N/A | V54: CIUDADANO (A) | W54: ATENCIÓN AL PUEBLO | X54: 2.- ALUMBRADO PÚBLICO | Y54: 45 OMITLÁN DE JUÁREZ | Z54: BARRIO DEL ESPEJO | AA54: MASCULINO | AB54: 7717082142 | AC54: barriodelaviadero2025@gmail.com | AD54: 1 | AE54: =AF54/4 -> 50 | AF54: 200 | AG54: CENTRO ORIENTE | AH54: ZONA PACHUCA
A55: 53 | B55: 152 | C55: FEBRERO | D55: 46073 | E55: SEDECO /CGI/TI/0193/2026 SDPEE/DGAP/547/2026 | F55: AEEH-2*1S.1/01-2026 ASESORIAS EN MATERIA ENERGÉTICA (VARIOS MUNICIPIOS) | G55: SOLICITA ATENDER A LA C. ELIDA MARTÍNEZ HERNÁNDEZ, QUIEN SOLICITA APOYO CON EL SERVICIO DE LUZ EN LA COLONIA HUMBERTA. | H55: ING. FRANCISCO | I55: ALTO | J55: 46078 | K55: SI | L55: SDE-UCC-07908-26 | M55: AEEH/DG/171/2026, DE FECHA 27/02/2026, ENVIADO AL ING. OCTAVIO GÓMEZ PAULIN. AEEH/DG/195/2026, DE FECHA 09/03/2026, ENVIADO AL ING. OCTAVIO GÓMEZ PAULIN. | N55: SI | O55: AEEH/DG/0731/2026, DE FECHA 03/08/2026, ENVIADO AL ING. HUGO ALEJANDRO ABUNDIS GONZÁLEZ | P55: NO | Q55: N/A | R55: N/A | S55: N/A | T55: N/A | U55: N/A | V55: CIUDADANO (A) | W55: ATENCIÓN AL PUEBLO | X55: 3.- ELECTRIFICACIÓN | Y55: 11 ATLAPEXCO | Z55: HUMBERTA | AA55: FEMENINO | AB55: 7713439854 | AD55: 1 | AE55: =AF55/4 -> 5 | AF55: 20 | AG55: GOLFO CENTRO | AH55: ZONA HUEJUTLA
A56: 54 | B56: 153 | C56: FEBRERO | D56: 46073 | E56: SEDECO /CGI/TI/0194/2026 SDPEE/DGAP/555/2026 | F56: AEEH-2*1S.1/01-2026 ASESORIAS EN MATERIA ENERGÉTICA (VARIOS MUNICIPIOS) | G56: ATENDER AL C. ERNESTO SOTO CASTAÑEDA, QUIEN SOLICITA APOYO CON LA COLOCACIÓN DE ALUMBRADO PÚBLICO EN SU LOCALIDAD | H56: ING. FRANCISCO | I56: ALTO | J56: 46078 | K56: SI | L56: SDE-UCC-07909-26 | M56: AEEH/DG/172/2026, DE FECHA 27/02/2026, ENVIADO AL ING. OCTAVIO GÓMEZ PAULIN. AEEH/DG/196/2026, DE FECHA 09/03/2026, ENVIADO AL ING. OCTAVIO GÓMEZ PAULIN. | N56: NO | O56: N/A | P56: N/A | Q56: N/A | R56: N/A | S56: N/A | T56: N/A | U56: N/A | V56: CIUDADANO (A) | W56: ATENCIÓN AL PUEBLO | X56: 2.- ALUMBRADO PÚBLICO | Y56: 45 OMITLÁN DE JUÁREZ | Z56: BARRIO DEL AVIADERO | AA56: MASCULINO | AB56: 7717082142 | AC56: barriodelaviadero2025@gmail.com | AD56: 1 | AE56: =AF56/4 -> 50 | AF56: 200 | AG56: CENTRO ORIENTE | AH56: ZONA PACHUCA
A57: 55 | B57: 158 | C57: FEBRERO | D57: 46076 | E57: SDPEE/DGAP/602/2026 SEDECO /CGI/TI/0203/2026 | F57: AEEH-2*1S.1/01-2026 ASESORIAS EN MATERIA ENERGÉTICA (VARIOS MUNICIPIOS) | G57: ATENDER A LA C. BERTHA MORALES QUIEN SOLICITA APOYO CON LA COLOCACIÓN DE ALUMBRADO PÚBLICO, DEBIDO A LOS DAÑOS OCASIONADOS POR LAS OBRAS DE CONSTRUCCIÓN EN LA AUTOPISTA REAL DEL MONTE - CRUCERO DE HUASCA | H57: ING. FRANCISCO | I57: ALTO | J57: 46078 | K57: SI | L57: SDE-UCC-07934-26 | M57: AEEH/DG/173/2026, DE FECHA 27/02/2026 ENVIADO AL ING. OCTAVIO GÓMEZ PAULIN AEEH/DG/197/2026, DE FECHA 09/03/2026 ENVIADO AL ING. OCTAVIO GÓMEZ PAULIN | N57: NO | O57: N/A | P57: N/A | Q57: N/A | R57: N/A | S57: N/A | T57: N/A | U57: N/A | V57: CIUDADANO (A) | W57: ATENCIÓN AL PUEBLO | X57: 2.- ALUMBRADO PÚBLICO | Y57: 45 OMITLÁN DE JUÁREZ | Z57: RINCON CHICO | AA57: FEMENINO | AB57: 7714240336 | AD57: 1 | AE57: =AF57/4 -> 72 | AF57: 288 | AG57: CENTRO ORIENTE | AH57: ZONA PACHUCA
A58: 56 | B58: 172 | C58: FEBRERO | D58: 46080 | E58: SEDECO/CGI/TI/0219/2026 SDPEE/DGAP/659/2026 | F58: AEEH-2*1S.1/01-2026 ASESORIAS EN MATERIA ENERGÉTICA (VARIOS MUNICIPIOS) | G58: ATENDER AL C. MARTIN LUGO PÉREZ QUIEN SOLICITA APOYO CON LA AMPLIACIÓN DE LA RED ELÉCTRICA EN EL EJIDO "PALMILLAS". | H58: ING. FRANCISCO | I58: ALTO | J58: 46080 | K58: SI | L58: SDE-UCC-07952-26 | M58: AEEH/DG/182/2026, DE FECHA 03/03/2026, ENVIADO AL ING. OCTAVIO GÓMEZ PAULIN. AEEH/DG/200/2026, DE FECHA 10/03/2026, ENVIADO AL ING. OCTAVIO GÓMEZ PAULIN. | N58: NO | O58: N/A | P58: N/A | Q58: N/A | R58: N/A | S58: N/A | T58: N/A | U58: N/A | V58: CIUDADANO (A) | W58: ATENCIÓN AL PUEBLO | X58: 3.- ELECTRIFICACIÓN | Y58: 24 HUASCA DE OCAMPO | Z58: EJIDO PALMILLAS | AA58: MASCULINO | AB58: 7712447808 | AD58: 1 | AE58: =AF58/4 -> 4 | AF58: 16 | AG58: CENTRO ORIENTE | AH58: ZONA PACHUCA
A59: 57 | B59: 173 | C59: FEBRERO | D59: 46080 | E59: SEDECO/CGI/TI/0220/2026 SDPEE/DGAP/686/2026 | F59: AEEH-2*1S.1/01-2026 ASESORIAS EN MATERIA ENERGÉTICA (VARIOS MUNICIPIOS) | G59: ATENDER AL C. HÉCTOR MANUEL MENESES PADILLA, QUIEN SOLICITA APOYO CON INTERVENCIÓN ANTE PRESUNTO COBRRO DE UN SERVICIO DE CFE EL CUAL NO HIZO USO | H59: ING. FRANCISCO | I59: ALTO | J59: 46080 | K59: SI | L59: SDE-UCC-07960-26 | M59: AEEH/DG/183/2026, DE FECHA 03/03/2026, ENVIADO AL ING. OCTAVIO GÓMEZ PAULIN. | N59: SI | O59: AEEH/DG/231/2026, DE FECHA 23/03/2026, ENVIADO AL ING. VICTOR ISRAEL ALARCON HEREDIA. | P59: SI | Q59: VAH-029-2026 | R59: N/A | S59: N/A | T59: N/A | U59: N/A | V59: CIUDADANO (A) | W59: ATENCIÓN AL PUEBLO | X59: 1.- ADEUDO | Y59: 82 ZAPOTLÁN DE JUÁREZ | Z59: JAGUEY DE TELLEZ | AA59: MASCULINO | AB59: 771 206 3154 | AD59: 1 | AE59: =AF59/4 -> 1 | AF59: 4 | AG59: CENTRO ORIENTE | AH59: ZONA PACHUCA
A60: 58 | B60: 182 | C60: MARZO | D60: 46083 | E60: SEDECO/CGI/TI/0232/2026 SDPEE/DGAP/745/2026 | F60: AEEH-2*1S.1/01-2026 ASESORIAS EN MATERIA ENERGÉTICA (VARIOS MUNICIPIOS) | G60: ATENDER A LA C. ÁNGELA HERNÁNDEZ GARAY QUIEN SOLICITA APOYO PARA LA ADQUISICIÓN Y COLOCACIÓN DE UN POSTE DE ENERGÍA ELÉCTRICA | H60: ING. FRANCISCO | I60: ALTO | J60: 46086 | K60: SI | L60: SDE-UC-00114-26 | M60: AEEH/DG/184/2026 DE FECHA 03/03/2026, ENVIADO AL ING. OCTAVIO GÓMEZ PAULIN AEEH/DG/233/2026 DE FECHA 23/03/2026, ENVIADO AL ING. OCTAVIO GÓMEZ PAULIN | N60: N/A | O60: N/A | P60: N/A | Q60: N/A | R60: N/A | S60: N/A | T60: N/A | U60: N/A | V60: CIUDADANO (A) | W60: ATENCIÓN AL PUEBLO | X60: 3.- ELECTRIFICACIÓN | Y60: 18 CHAPULHUACÁN | Z60: LA ESCONDIDA | AA60: FEMENINO | AB60: 771 346 9962 | AD60: 1 | AE60: =AF60/4 -> 4 | AF60: 16 | AG60: DIVISION BAJIO | AH60: ZONA IXMIQUILPAN
A61: 59 | B61: 198 | C61: MARZO | D61: 46085 | E61: SEDECO/CGI/TI/0251/2026 SDPEE/DGAP/782/2026 | F61: AEEH-2*1S.1/01-2026 ASESORIAS EN MATERIA ENERGÉTICA (VARIOS MUNICIPIOS) | G61: ATENDER A LA C. FÉLIX SÁNCHEZ LICONA, QUIEN SOLICITA APOYO CON LA INSTALACIÓN DE ALUMBRADO PÚBLICO EN CAMINO DE SU LOCALIDAD | H61: ING. FRANCISCO | I61: ALTO | J61: 46087 | K61: SI | L61: SDE-UC-00018-26 SDE-CGI-00239-26 | M61: AEEH/DG/201/2026, DE FECHA 10/03/2026, ENVIADO AL ING. OCTAVIO GÓMEZ PAULIN. AEEH/DG/236/2026, DE FECHA 23/03/2026, ENVIADO AL ING. OCTAVIO GÓMEZ PAULIN. | N61: N/A | O61: N/A | P61: N/A | Q61: N/A | R61: SI | S61: AEEH/DG/241/2026, DE FECHA 23/03/2026, ENVIADO A LA C. MARTHA BELEM OLIVER GONZÁLEZ, PRESIDENTA MUINICIPAL DE OMITLAN DE JUAREZ. | T61: NO | U61: N/A | V61: CIUDADANO (A) | W61: ATENCIÓN AL PUEBLO | X61: 2.- ALUMBRADO PÚBLICO | Y61: 45 OMITLÁN DE JUÁREZ | Z61: EL PLAN TAPANCOS | AA61: MASCULINO | AB61: 7711879427 | AC61: fey.sanchez036@gmail.com | AD61: 1 | AE61: 63 | AF61: 250 | AG61: CENTRO ORIENTE | AH61: ZONA PACHUCA
A62: 60 | B62: 194 | C62: MARZO | D62: 46085 | E62: SEDECO/CGI/TI/0233/2026 SDPEE/DGAP/756/026 | F62: AEEH-2*1S.1/01-2026 ASESORIAS EN MATERIA ENERGÉTICA (VARIOS MUNICIPIOS) | G62: ATENDER A LA C. ROSA ICELA GODINEZ CARMONA, QUIEN SOLICITA APOYO PARA LA ADQUISICIÓN DE UN SISTEMA DE FOTOCELDA PARA EL PREESCOLAR COMUNITARIO MONTESSORI | H62: ING. FRANCISCO | I62: ALTO | J62: 46087 | K62: SI | L62: SDE-UCC-07987-26 | M62: AEEH/DG/202/2026, DE FECHA 10/03/2026, ENVIADO AL ING. OCTAVIO GÓMEZ PAULIN, COORDINADOR DE GESTIÓN INSTITUCIONAL AEEH/DG/237/2026, DE FECHA 23/03/2026, ENVIADO AL ING. OCTAVIO GÓMEZ PAULIN, COORDINADOR DE GESTIÓN INSTITUCIONAL AEEH/DG/398/2026, DE FECHA 29/04/2026, ENVIADO AL ING. OCTAVIO GÓMEZ PAULIN, COORDINADOR DE GESTIÓN INSTITUCIONAL | N62: N/A | O62: N/A | P62: N/A | Q62: N/A | R62: N/A | S62: N/A | T62: N/A | U62: N/A | V62: CIUDADANO (A) | W62: ATENCIÓN AL PUEBLO | X62: 4.- ENERGÍA RENOVABLE (SOLAR, EÓLICA) | Y62: 35 METEPEC | Z62: LA LOMA | AA62: FEMENINO | AB62: 7711966663 | AD62: 1 | AE62: =AF62/4 -> 10 | AF62: 40 | AG62: GOLFO CENTRO | AH62: ZONA HUEJUTLA
A63: 61 | B63: 197 | C63: MARZO | D63: 46085 | E63: SEDECO/CGI/TI/0250/2026 SDPEE/DGAP/708/026 | F63: AEEH-2*1S.1/01-2026 ASESORIAS EN MATERIA ENERGÉTICA (VARIOS MUNICIPIOS) | G63: ATENDER AL C. FERMIN CISNEROS CISNEROS, QUIEN SOLICITA MEDIACIÓN CON AYUNTAMIENTO PARA QUE OTORGUE PERMISOS PARA CONCLUIR LA AMPLIACIÓN DE LA RED ELECTRICA DE SU LOCALIDAD. | H63: ING. FRANCISCO | I63: ALTO | J63: 46087 | K63: SI | L63: SDE-UC-00017-26 SDE-CGI-00253-26 | M63: AEEH/DG/203/2026, DE FECHA 10/03/2026, ENVIADO AL ING. OCTAVIO GÓMEZ PAULIN. | N63: SI | O63: AEEH/DG/310/2026, DE FECHA 10/03/2026, ENVIADO AL MTRO. JESÚS IVÁN RODRÍGUEZ LÓPEZ, SUBDIRECTOR DE INGENIERÍA Y ADMINISTRACIÓN DE LA CONSTRUCCIÓN - CFE | P63: SI | Q63: SDZDDH/00116/2026 | R63: N/A | S63: N/A | T63: N/A | U63: N/A | V63: CIUDADANO (A) | W63: ATENCIÓN AL PUEBLO | X63: 3.- ELECTRIFICACIÓN | Y63: 14 CALNALI | Z63: Pezmatlan | AA63: MASCULINO | AB63: 7711126790 | AC63: fermincisneros272@gmail.com | AD63: 1 | AE63: =AF63/4 -> 19 | AF63: 76 | AG63: GOLFO CENTRO | AH63: ZONA HUEJUTLA
A64: 62 | B64: 227 | C64: MARZO | D64: 46092 | E64: SEDECO/SIyES/DGES/031/2026 | F64: AEEH-2*1S.4/01-2026 PROMOCIONES TÉCNICAS EN MATERIA ENERGÉTICA (POELP) | G64: LA SUBSECRETARIA DE INVERSIONES Y ECONOMIA SECTORIAL SOLICITA LAS COORDENADAS GEOGRAFICAS DE POLIGONOS IDENTIFICADOS PARA EL DERARROLLO DE PROYECTOS U OBRAS PROPUESTAS POR SEDECO (POELP MINERAL DE LA REFORMA) | H64: ARQ. DIEGO | I64: ALTO | J64: 46094 | K64: SI | L64: SDE-DGES-00424-26 | M64: AEEH/DG/224/2026, DE FECHA 23/03/2026, ENVIADO AL ARQ. ERNESTO CADENA ACOSTA | N64: N/A | O64: N/A | P64: N/A | Q64: N/A | R64: N/A | S64: N/A | T64: N/A | U64: N/A | V64: DEPENDENCIA ESTATAL | W64: OTRAS INSTANCIAS | X64: 7.- INVITACIONES/EXPOS/CONGRESOS/TEMAS ADMINISTRATIVOS/CAPACITACIONES/ATENCIÓN A EMPRESAS/ELECTROMOVILIDAD/OTROS | AA64: MASCULINO | AB64: 771 688 6026 | AD64: 1 | AE64: 1 | AF64: 0 | AG64: N/A | AH64: N/A
A65: 63 | B65: 166 | C65: FEBRERO | D65: 46079 | E65: TELECOM/CT/070/2026 | F65: AEEH-2*1S.1/17-2025 ASESORIAS EN MATERIA DE TELECOMUNICACIONES (VARIOS MUNICIPIOS) | G65: SOLICITUDES DE CONECTIVIDAD (TELEFONÍA E INTERNET) A DIVERSAS COMUNIDADES DEL ESTADO DE HIDALGO | H65: ARQ. DIEGO | I65: ALTO | J65: 46079 | K65: SI | L65: GESTIÓN 2025 SDE-AEEH-00333-25 | M65: AEEH/DG/226/2026, DE FECHA 23/03/2026, ENVIADO A LA MTRA. LILIANA BARRERA JIMÉNEZ SUBDIRECTORA DE ESTRATEGIA COMERCIAL | N65: NO | O65: N/A | P65: N/A | Q65: N/A | R65: N/A | S65: N/A | T65: N/A | U65: N/A | V65: DEPENDENCIA FEDERAL | W65: SEGUIMIENTO A SOLICITUDES | X65: 12.- SEGUIMIENTO A SOLICITUDES | AD65: 0 | AE65: =AF65/4 -> 0 | AF65: 0 | AG65: N/A | AH65: N/A
A66: 64 | B66: 203 | C66: MARZO | D66: 46086 | E66: SEDECO/CGI/TI/0268/2026 | F66: AEEH-2*1S.1/01-2026 ASESORIAS EN MATERIA ENERGÉTICA (VARIOS MUNICIPIOS) | G66: ATENDER AL C. DANIEL ORTÍZ VÁZQUEZ, QUIEN SOLICITA APOYO PARA EL REEMPLAZO DE LUMINARIAS DE ALUMBRADO PÚBLICO EN SU COMUNIDAD | H66: ING. FRANCISCO | I66: ALTO | J66: 46091 | K66: SI | L66: SDE-CGI-00238-26 | M66: AEEH/DG/232/2026, DE FECHA 23/03/2026, ENVIDO AL ING. OCTAVIO GÓMEZ PAULIN | N66: NO | O66: N/A | P66: N/A | Q66: N/A | R66: N/A | S66: N/A | T66: N/A | U66: N/A | V66: AYUNTAMIENTO | W66: OTRAS INSTANCIAS | X66: 2.- ALUMBRADO PÚBLICO | Y66: 35 METEPEC | Z66: COL. CENTRO | AA66: MASCULINO | AB66: 7751502897 | AC66: presidencia@metepechidalgo.gob.mx | AD66: 1 | AE66: =AF66/4 -> 400 | AF66: 1600 | AG66: GOLFO CENTRO | AH66: ZONA HUEJUTLA
A67: 65 | B67: 202 | C67: MARZO | D67: 46086 | E67: SEDECO/CGI/TI/0256/2026 SDPEE/DGAP/846/2026 | F67: AEEH-2*1S.1/01-2026 ASESORIAS EN MATERIA ENERGÉTICA (VARIOS MUNICIPIOS) | G67: ATENDER A LA C. MARÍA FELIX ESPAÑA ROMERO, QUIEN SOLICITA APOYO CON LA INSTALACIÓN DE RED ELECTRICA PARA SU DOMICILIO | H67: ING. FRANCISCO | I67: ALTO | J67: 46091 | K67: SI | L67: SDE-UC-00051-26 | M67: AEEH/DG/234/2026, DE FECHA 23/03/2026, ENVIADO AL ING. OCTAVIO GÓMEZ PAULIN. | N67: SI | O67: AEEH/DG/0731/2026, DE FECHA 03/08/2026, ENVIADO AL ING. HUGO ALEJANDRO ABUNDIS GONZÁLEZ | P67: NO | Q67: N/A | R67: N/A | S67: N/A | T67: N/A | U67: N/A | V67: CIUDADANO (A) | W67: ATENCIÓN AL PUEBLO | X67: 3.- ELECTRIFICACIÓN | Y67: 4 AGUA BLANCA DE ITURBIDE | Z67: EJIDO LOMA ANCHA | AA67: FEMENINO | AB67: 7751099841 | AD67: 1 | AE67: =AF67/4 -> 1 | AF67: 4 | AG67: GOLFO CENTRO | AH67: ZONA HUEJUTLA
A68: 66 | B68: 204 | C68: MARZO | D68: 46086 | E68: SEDECO/CGI/TI/0268/2026 SDPEE/DGAP/893/2026 | F68: AEEH-2*1S.1/01-2026 ASESORIAS EN MATERIA ENERGÉTICA (VARIOS MUNICIPIOS) | G68: ATENDER A FERNADO DEL RAZO OMAÑA, QUIEN SOLICITA APOYO CON LA AMPLIACIÓN DE LA RED ELECTRICA Y ALUMBRADO PÚBLICO EN SU LOCALIDAD. | H68: ING. FRANCISCO | I68: ALTO | J68: 46091 | K68: SI | L68: SDE-UC-00052-26 | M68: AEEH/DG/235/2026, DE FECHA 23/03/2026, ENVIADO AL ING. OCTAVIO GÓMEZ PAULIN. | N68: NO | O68: N/A | P68: N/A | Q68: N/A | R68: SI | S68: AEEH/DG/453/2026, DE FECHA 20/05/2026, ENVIADO A LA C. MA. YANET FERNÁNDEZ FERNÁNDEZ, PRESIDENTA MUNICIPAL DE SANTIAGO TULANTEPEC | T68: N/A | U68: N/A | V68: CIUDADANO (A) | W68: ATENCIÓN AL PUEBLO | X68: 3.- ELECTRIFICACIÓN | Y68: 56 SANTIAGO TULANTEPEC DE LUGO GUERRERO | Z68: SAN PEDRO HUATENGO | AA68: MASCULINO | AB68: 7752244625 | AC68: 27fernando.71@gmail.com | AD68: 1 | AE68: =AF68/4 -> 33 | AF68: 132 | AG68: CENTRO ORIENTE | AH68: ZONA TULANCINGO
A69: 67 | B69: 226 | C69: MARZO | D69: 46092 | E69: SEDECO/CGI/TI/0299/2026 SDPEE/DGAP/1066/2026 | F69: AEEH-2*1S.1/01-2026 ASESORIAS EN MATERIA ENERGÉTICA (VARIOS MUNICIPIOS) | G69: ATENDER AL C. FRANCISCO SIERRA HERNÁNDEZ, QUIEN SOLICITA APOYO CON EL SERVICIO DE ELECTRIFICACIÓN | H69: ING. FRANCISCO | I69: ALTO | J69: 46094 | K69: SI | L69: SDE-UC-00115-26 | M69: AEEH/DG/239/2026, DE FECHA 23/03/2026, ENVIADO AL ING. OCTAVIO GÓMEZ PAULIN. AEEH/DG/279/2026, DE FECHA 31/03/2026, ENVIADO AL ING. OCTAVIO GÓMEZ PAULIN. | N69: NO | O69: N/A | P69: N/A | Q69: N/A | R69: N/A | S69: N/A | T69: N/A | U69: N/A | V69: CIUDADANO (A) | W69: ATENCIÓN AL PUEBLO | X69: 2.- ALUMBRADO PÚBLICO | Y69: 9 EL ARENAL | Z69: OJO DE AGUA | AA69: MASCULINO | AB69: 6131161333 | AD69: 1 | AE69: =AF69/4 -> 46 | AF69: 184 | AG69: CENTRO ORIENTE | AH69: ZONA PACHUCA
A70: 68 | B70: 224 | C70: MARZO | D70: 46092 | E70: SEDECO/CGI/TI/0282/2026 SDPEE/DGAP/993/2026 | F70: AEEH-2*1S.1/01-2026 ASESORIAS EN MATERIA ENERGÉTICA (VARIOS MUNICIPIOS) | G70: ATENDER AL DELEGADO LEOPOLDO DÍAZ BERISTAIN, QUIEN SOLICITA REALIZAR LA MODERNICACÍON Y AMPLIACIÓN DE LA RED DE ALUMBRADO PÚBLICO DE SU COMUNIDAD | H70: ING. FRANCISCO | I70: ALTO | J70: 46094 | K70: SI | L70: SDE-UC-00091-26 | M70: AEEH/DG/240/2026, DE FECHA 23/03/2026, ENVIADO AL ING. OCTAVIO GÓMEZ PAULIN. AEEH/DG/277/2026, DE FECHA 31/03/2026, ENVIADO AL ING. OCTAVIO GÓMEZ PAULIN. | N70: NO | O70: N/A | P70: N/A | Q70: N/A | R70: N/A | S70: N/A | T70: N/A | U70: N/A | V70: DELEGADO (A) MUNICIPAL | W70: ATENCIÓN AL PUEBLO | X70: 2.- ALUMBRADO PÚBLICO | Y70: 8 APAN | Z70: LÁZARO CARDENAS | AA70: MASCULINO | AB70: 7712019852 | AD70: 1 | AE70: =AF70/4 -> 30 | AF70: 120 | AG70: CENTRO ORIENTE | AH70: ZONA TULANCINGO
A71: 69 | B71: 233 | C71: MARZO | D71: 46094 | E71: SEDECO/CGI/TI/0307/2026 SDPEE/DGAP/1139/2026 | F71: AEEH-2*1S.1/01-2026 ASESORIAS EN MATERIA ENERGÉTICA (VARIOS MUNICIPIOS) | G71: ATENDER A JUAN CARLOS VITE GUERRERO, QUIEN SOLICITA LA DONACIÓN DE 15 LAMPARAS DE ALUMBRADO PUBLICO. | H71: ING. FRANCISCO | I71: ALTO | J71: 46100 | K71: SI | L71: SDE-UC-00135-26 | M71: AEEH/DG/243/2026, DE FECHA 23/03/2026, ENVIADO AL ING. OCTAVIO GOMEZ PAULIN AEEH/DG/280/2026, DE FECHA 31/03/2026, ENVIADO AL ING. OCTAVIO GOMEZ PAULIN | N71: N/A | O71: N/A | P71: N/A | Q71: N/A | R71: N/A | S71: N/A | T71: N/A | U71: N/A | V71: CIUDADANO (A) | W71: ATENCIÓN AL PUEBLO | X71: 2.- ALUMBRADO PÚBLICO | Y71: 2 ACAXOCHITLÁN | Z71: TECOJOTAL | AA71: MASCULINO | AB71: 7712089709 | AC71: viteguerrerojuancarlos@gmail.com | AD71: 1 | AE71: 203 | AF71: 810 | AG71: CENTRO ORIENTE | AH71: ZONA TULANCINGO
A72: 70 | B72: 258 | C72: MARZO | D72: 46101 | E72: SEDECO/CGI/TI/0349/2026 SDPEE/DGAP/1394/2026 | F72: AEEH-2*1S.1/01-2026 ASESORIAS EN MATERIA ENERGÉTICA (VARIOS MUNICIPIOS) | G72: ATENDER A LA C. MA. EUGENIA MONROY LOPEZ, QUIEN SOLICITA APOYO PARA QUE SU VIVIENDA CUENTE CON SERVICIO DE ENERGIA ELECTRICA | H72: ING. FRANCISCO | I72: ALTO | J72: 46105 | K72: SI | L72: SDE-UC-00191-26 | M72: AEEH/DG/257/2026, DE FECHA 27/03/2026, ENVIADO AL ING. OCTAVIO GOMEZ PAULIN. AEEH/DG/303/2026, DE FECHA 08/04/2026, ENVIADO AL ING. OCTAVIO GOMEZ PAULIN COORDINADOR DE GESTION INSTITUCIONAL. | N72: NO | O72: N/A | P72: N/A | Q72: N/A | R72: SI | S72: AEEH/DG/392/2026, DE FECHA 28/04/2026, ENVIADO A LA C. MA. EUGENIA MONROY LÓPEZ, PETICIONARIA DEL MUNICIPIO DE TEPEAPULCO. | T72: NO | U72: N/A | V72: CIUDADANO (A) | W72: ATENCIÓN AL PUEBLO | X72: 3.- ELECTRIFICACIÓN | Y72: 61 TEPEAPULCO | Z72: SAHAGUN | AA72: FEMENINO | AB72: 7713932455 | AD72: 1 | AE72: =AF72/4 -> 1 | AF72: 4 | AG72: CENTRO ORIENTE | AH72: ZONA TULANCINGO
A73: 71 | B73: 253 | C73: MARZO | D73: 46101 | E73: SEDECO/CGI/TI/0317/2026 SDPEE/DGAP/1203/2026 | F73: AEEH-2*1S.1/01-2026 ASESORIAS EN MATERIA ENERGÉTICA (VARIOS MUNICIPIOS) | G73: ATENDER A LA C. MARIA FELIX GALICIA CHILINO, QUIEN SOLICITA APOYO PARA ACCEDER AL SERVICIO DE ENERGIA ELECTRICA EN SU DOMICILIO | H73: ING. FRANCISCO | I73: ALTO | J73: 46105 | K73: SI | L73: SDE-UC-00137-26 | M73: AEEH/DG/258/2026, DE FECHA 27/03/2026, ENVIADO AL ING. OCTAVIO GÓMEZ PAULIN. | N73: SI | O73: AEEH/DG/308/2026, DE FECHA 10/04/2026, ENVIADO AL ING. GILBERTO LEÓN ORDAZ, SUPERINTENDENTE EF - CFE ZONA TULANCINGO | P73: SI | Q73: GLO-099-2026 | R73: N/A | S73: N/A | T73: N/A | U73: N/A | V73: CIUDADANO (A) | W73: ATENCIÓN AL PUEBLO | X73: 3.- ELECTRIFICACIÓN | Y73: 2 ACAXOCHITLÁN | Z73: TLAMIMILOLPA | AA73: FEMENINO | AB73: 7711222241 | AD73: 1 | AE73: =AF73/4 -> 1 | AF73: 4 | AG73: CENTRO ORIENTE | AH73: ZONA TULANCINGO
A74: 72 | B74: 257 | C74: MARZO | D74: 46101 | E74: SEDECO/CGI/TI/0347/2026 SDPEE/DGAP/1403/2026 | F74: AEEH-2*1S.1/01-2026 ASESORIAS EN MATERIA ENERGÉTICA (VARIOS MUNICIPIOS) | G74: ATENDER AL C. FEDERICO ALFREDO CAZAREZ LOPEZ, QUIEN SOLICITA APOYO PARA REUBICAR UN POSTE DE ENERGIA ELECTRICA QUE SE ENCUENTRA EN SU PROPIEDAD. | H74: ING. FRANCISCO | I74: ALTO | J74: 46105 | K74: SI | L74: SDE-UC-00198-26 | M74: AEEH/DG/259/2026, DE FECHA 27/03/2026, ENVIADO AL ING. OCTAVIO GÓMEZ PAULIN. AEEH/DG/290/2026, DE FECHA 06/04/2026, ENVIADO AL ING. OCTAVIO GÓMEZ PAULIN. | N74: SI | O74: AEEH/DG/307/2026, DE FECHA 10/04/2026, ENVIADO AL ING. GILBERTO LEON ORDAZ SUPERINTENDENTE EF - CFE ZONA TULANCINGO | P74: SI | Q74: MMHR-223-2026 GLO-123-2026 | R74: N/A | S74: N/A | T74: N/A | U74: N/A | V74: CIUDADANO (A) | W74: ATENCIÓN AL PUEBLO | X74: 8.- MEJORAS A LA RED | Y74: 61 TEPEAPULCO | AA74: MASCULINO | AB74: 7911003559 | AC74: CITLALLI.CAZARESDEJESUS@GMAIL.COM | AD74: 1 | AE74: =AF74/4 -> 1 | AF74: 4 | AG74: CENTRO ORIENTE | AH74: ZONA TULANCINGO
A75: 73 | B75: 259 | C75: MARZO | D75: 46101 | E75: SEDECO/CGI/TI/0353/2026 SDPEE/DGAP/1414/2026 | F75: AEEH-2*1S.1/01-2026 ASESORIAS EN MATERIA ENERGÉTICA (VARIOS MUNICIPIOS) | G75: ATENDER A LA C. JULIA CALZADA, QUIEN SOLICITA LA COLOCACIÓN DE LUMINARIAS EN LA AVENIDA PRINCIPAL DE SU LOCALIDAD | H75: ING. FRANCISCO | I75: ALTO | J75: 46105 | K75: SI | L75: SDE-UC-00201-26 | M75: AEEH/DG/260/2026, DE FECHA 27/03/2026, ENVIADO AL ING. OCTAVIO GÓMEZ PAULIN. AEEH/DG/291/2026, DE FECHA 06/04/2026, ENVIADO AL ING. OCTAVIO GÓMEZ PAULIN. | N75: NO | O75: N/A | P75: N/A | Q75: N/A | R75: N/A | S75: N/A | T75: N/A | U75: N/A | V75: CIUDADANO (A) | W75: ATENCIÓN AL PUEBLO | X75: 2.- ALUMBRADO PÚBLICO | Y75: 61 TEPEAPULCO | AA75: FEMENINO | AB75: 5614833301 | AD75: 1 | AE75: =AF75/4 -> 37.5 | AF75: 150 | AG75: CENTRO ORIENTE | AH75: ZONA TULANCINGO
A76: 74 | B76: 251 | C76: MARZO | D76: 46100 | E76: SEDECO/CAYP/0366/2026 | F76: AEEH-2*1S.3/06-2026 PROYECTO DE OFICINAS DE LA AEEH | G76: SOLICITUD DE INFORMACIÓN PARA EL PROYECTO DE LA REUBICACIÓN DE LAS OFICINAS DE LA SECRETARÍA DE DESARROLLO ECONOMICO Y ORGANISMOS DESCENTRALIZADOS | H76: ARQ. DIEGO | I76: ALTO | J76: 46105 | K76: SI | L76: SDE-SRMAT-00254-26 | M76: AEEH/DG/262/2026, DE FECHA 27/03/2026, ENVIADO A LA MTRA. JESSICA ESPERANZA GONZÁLEZ DÍAZ, COORDINADORA DE ADMINISTRACIÓN Y PLANEACIÓN DE SEDECO | N76: N/A | O76: N/A | P76: N/A | Q76: N/A | R76: N/A | S76: N/A | T76: N/A | U76: N/A | V76: DEPENDENCIA ESTATAL | W76: OTRAS INSTANCIAS | X76: 7.- INVITACIONES/EXPOS/CONGRESOS/TEMAS ADMINISTRATIVOS/CAPACITACIONES/ATENCIÓN A EMPRESAS/ELECTROMOVILIDAD/OTROS | AA76: FEMENINO | AD76: 1 | AE76: 1 | AF76: 0 | AG76: N/A | AH76: N/A
A77: 75 | B77: 256 | C77: MARZO | D77: 46101 | E77: SEDECO/CGI/TI/0325/2026 SDPEE/DGAP/1317/2026 | F77: AEEH-2*1S.1/01-2026 ASESORIAS EN MATERIA ENERGÉTICA (VARIOS MUNICIPIOS) | G77: ATENDER AL C. JOEL SANCHEZ SANTOS, QUIEN SOLICITA APOYO PARA QUE PUEDA CONTAR CON SERVICIO DE ENERGIA ELÉCTRICA EN SU LOCALIDAD | H77: ING. FRANCISCO | I77: ALTO | J77: 46105 | K77: SI | L77: SDE-UC-00173-26 | M77: AEEH/DG/282/2026, DE FECHA 31/03/2026, ENVIADO AL ING. OCTAVIO GÓMEZ PAULIN. AEEH/DG/289/2026, DE FECHA 06/04/2026, ENVIADO AL ING. OCTAVIO GÓMEZ PAULIN. | N77: NO | O77: N/A | P77: N/A | Q77: N/A | R77: N/A | S77: N/A | T77: N/A | U77: N/A | V77: CIUDADANO (A) | W77: ATENCIÓN AL PUEBLO | X77: 3.- ELECTRIFICACIÓN | Y77: 83 ZEMPOALA | Z77: LA OLLA | AA77: MASCULINO | AB77: 7711501712 | AC77: smarikarla@yahoo.com.mx | AD77: 1 | AE77: 17 | AF77: 67 | AG77: CENTRO ORIENTE | AH77: ZONA PACHUCA
A78: 76 | B78: 268 | C78: MARZO | D78: 46111 | E78: SEDECO/CGI/TI/0365/2026 SDPEE/DGAP/1511/2026 | F78: AEEH-2*1S.1/01-2026 ASESORIAS EN MATERIA ENERGÉTICA (VARIOS MUNICIPIOS) | G78: ATENDER A LUCILA ISLAS GUTIERREZ, CON LA OBRA "AMPLIACIÓN DE RED DE LUZ ELECTRICA" | H78: ING. FRANCISCO | I78: ALTO | J78: 46111 | K78: SI | L78: SDE-UC-00236-26 | M78: AEEH/DG/292/2026, DE FECHA 06/04/2026, ENVIADO AL ING. OCTAVIO GÓMEZ PAULIN. | N78: SI | O78: AEEH/DG/347/2026, DE FECHA 17/04/2026, ENVIADO AL ING. VÍCTOR ISRAEL ALARCÓN HEREDIA, SUPERINTENDETNE DE LA CFE ZONA PACHUCA | P78: SI | Q78: MMHR-245-2026 | R78: N/A | S78: N/A | T78: N/A | U78: N/A | V78: CIUDADANO (A) | W78: ATENCIÓN AL PUEBLO | X78: 3.- ELECTRIFICACIÓN | Y78: 83 ZEMPOALA | Z78: COL. SAN RAFAEL | AA78: FEMENINO | AB78: 5536444499 | AD78: 1 | AE78: =AF78/4 -> 10 | AF78: 40 | AG78: CENTRO ORIENTE | AH78: ZONA PACHUCA
A79: 77 | B79: 269 | C79: MARZO | D79: 46111 | E79: SEDECO/CGI/TI/0366/2026 SDPEE/DGAP/1512/2026 | F79: AEEH-2*1S.1/01-2026 ASESORIAS EN MATERIA ENERGÉTICA (VARIOS MUNICIPIOS) | G79: ATENDER A LUCIA ISLAS GUTIERREZ, QUIEN SOLICITA APOYO CON LA INSTALACIÓN DE 10 LAMPARAS DE ALUMBRADO PÚBLICO EN SU COLONIA. | H79: ING. FRANCISCO | I79: ALTO | J79: 46111 | K79: SI | L79: SDE-UC-00235-26 | M79: AEEH/DG/293/2026, DE FECHA 06/04/2026, ENVIADO AL ING. OCTAVIO GÓMEZ PAULIN. | N79: NO | O79: N/A | P79: N/A | Q79: N/A | R79: SI | S79: AEEH/DG/391/2026, DE FECHA 28/04/2026, ENVIADO AL DR. FÉLIX ÁVILA CASTELÁN, PRESIDENTE MUNICIPAL CONSTITUCIONAL DE TEPEAPULCO. | T79: NO | U79: N/A | V79: CIUDADANO (A) | W79: ATENCIÓN AL PUEBLO | X79: 2.- ALUMBRADO PÚBLICO | Y79: 83 ZEMPOALA | Z79: COL. SAN RAFAEL | AA79: FEMENINO | AB79: 5536444499 | AD79: 1 | AE79: =AF79/4 -> 25 | AF79: 100 | AG79: CENTRO ORIENTE | AH79: ZONA PACHUCA
A80: 78 | B80: 270 | C80: MARZO | D80: 46111 | E80: SEDECO/CGI/TI/0367/2026 SDPEE/DGAP/1532/2026 | F80: AEEH-2*1S.1/01-2026 ASESORIAS EN MATERIA ENERGÉTICA (VARIOS MUNICIPIOS) | G80: ATENDER A JORGE ANTONIO CRAVIOTO BAUTISTA, QUIEN SOLICITA LA COLOCACIÓN DE 5 POSTES PARA LA AMPLIACIÓN DE LUZ EN SU COLONIA. | H80: ING. FRANCISCO | I80: ALTO | J80: 46111 | K80: SI | L80: SDE-UC-00237-26 | M80: AEEH/DG/294/2026, DE FECHA 06/04/2026, ENVIADO AL ING. OCTAVIO GÓMEZ PAULIN. AEEH/DG/343/2026, DE FECHA 17/04/2026, ENVIADO AL ING. OCTAVIO GÓMEZ PAULIN. | N80: NO | O80: N/A | P80: N/A | Q80: N/A | R80: N/A | S80: N/A | T80: N/A | U80: N/A | V80: CIUDADANO (A) | W80: ATENCIÓN AL PUEBLO | X80: 3.- ELECTRIFICACIÓN | Y80: 83 ZEMPOALA | Z80: SAN JUAN TEPEMAZALCO | AA80: MASCULINO | AB80: 7717734654 | AD80: 1 | AE80: =AF80/4 -> 20 | AF80: 80 | AG80: CENTRO ORIENTE | AH80: ZONA PACHUCA
A81: 79 | B81: 271 | C81: MARZO | D81: 46111 | E81: SEDECO/CGI/TI/0368/2026 SDPEE/DGAP/1568/2026 | F81: AEEH-2*1S.1/01-2026 ASESORIAS EN MATERIA ENERGÉTICA (VARIOS MUNICIPIOS) | G81: ATENDER A MARIA DE JESUS DE LUCIO IBARRA, QUIEN SOLICITA LA COLOCACIÓN DE 2 POSTES DE LUZ PARA LA AMPLIACIÓN DE ENERGIA ELECTRICA EN SU COMUNIDAD | H81: ING. FRANCISCO | I81: ALTO | J81: 46111 | K81: SI | L81: SDE-UC-00242-26 | M81: AEEH/DG/295/2026, DE FECHA 06/04/2026, ENVIADO AL ING. OCTAVIO GÓMEZ PAULIN. AEEH/DG/344/2026, DE FECHA 17/04/2026, ENVIADO AL ING. OCTAVIO GÓMEZ PAULIN. | N81: NO | O81: N/A | P81: N/A | Q81: N/A | R81: N/A | S81: N/A | T81: N/A | U81: N/A | V81: CIUDADANO (A) | W81: ATENCIÓN AL PUEBLO | X81: 3.- ELECTRIFICACIÓN | Y81: 83 ZEMPOALA | Z81: TEPEYAHUALCO | AA81: FEMENINO | AB81: 7711235578 | AD81: 1 | AE81: =AF81/4 -> 10 | AF81: 40 | AG81: CENTRO ORIENTE | AH81: ZONA PACHUCA
A82: 80 | B82: 272 | C82: MARZO | D82: 46111 | E82: SEDECO/CGI/TI/0369/2026 SDPEE/DGAP/1605/2026 | F82: AEEH-2*1S.1/01-2026 ASESORIAS EN MATERIA ENERGÉTICA (VARIOS MUNICIPIOS) | G82: ATENDER A ERNESTO VÁZQUEZ GÓMEZ, QUIEN SOLICITA LA ELECTRIFICACIÓN DE DIVERSAS CALLES DE SU LOCALIDAD | H82: ING. FRANCISCO | I82: ALTO | J82: 46111 | K82: SI | L82: SDE-UC-00257-26 | M82: AEEH/DG/296/2026, DE FECHA 06/04/2026, ENVIADO AL ING. OCTAVIO GÓMEZ PAULIN. AEEH/DG/345/2026, DE FECHA 17/04/2026, ENVIADO AL ING. OCTAVIO GÓMEZ PAULIN. | N82: N/A | O82: N/A | P82: N/A | Q82: N/A | R82: N/A | S82: N/A | T82: N/A | U82: N/A | V82: CIUDADANO (A) | W82: ATENCIÓN AL PUEBLO | X82: 2.- ALUMBRADO PÚBLICO | Y82: 22 EPAZOYUCAN | Z82: SAN JUAN TIZAHUAPAN | AA82: MASCULINO | AB82: 7711099070 | AD82: 1 | AE82: =AF82/4 -> 50 | AF82: 200 | AG82: CENTRO ORIENTE | AH82: ZONA PACHUCA
A83: 81 | B83: 274 | C83: MARZO | D83: 46111 | E83: SEDECO/CGI/TI/0375/2026 SDPEE/DGAP/1629/2026 | F83: AEEH-2*1S.1/01-2026 ASESORIAS EN MATERIA ENERGÉTICA (VARIOS MUNICIPIOS) | G83: ATENDER A GERMAN PEREZ BAUTISTA, QUIEN SOLICITA LA INTERVENCIÓN ANTE CFE PARA LA OBRA DE AMPLICIACIÓN DE RED ELECTRICA. | H83: ING. FRANCISCO | I83: ALTO | J83: 46111 | K83: SI | L83: SDE-UC-00260-26 | M83: AEEH/DG/297/2026, DE FECHA 06/04/2026, ENVIADO AL ING. OCTAVIO GÓMEZ PAULIN. AEEH/DG/346/2026, DE FECHA 17/04/2026, ENVIADO AL ING. OCTAVIO GÓMEZ PAULIN. AEEH/DG/506/2026, DE FECHA 05/06/2026, ENVIADO AL ING. OCTAVIO GÓMEZ PAULIN. | N83: NO | O83: N/A | P83: N/A | Q83: N/A | R83: N/A | S83: N/A | T83: N/A | U83: N/A | V83: CIUDADANO (A) | W83: ATENCIÓN AL PUEBLO | X83: 3.- ELECTRIFICACIÓN | Y83: 83 ZEMPOALA | Z83: SAN AGUSTIN ZAPOTLAN | AA83: MASCULINO | AB83: 7712469060 | AD83: 1 | AE83: 67 | AF83: 265 | AG83: CENTRO ORIENTE | AH83: ZONA PACHUCA
A84: 82 | B84: 285 | C84: ABRIL | D84: 46119 | E84: SEDECO/CGI/TI/0402/2026 SDPEE/DGAP/1674/2026 | F84: AEEH-2*1S.1/01-2026 ASESORIAS EN MATERIA ENERGÉTICA (VARIOS MUNICIPIOS) | G84: ATENDER A LA C. ANDREA GONZALEZ HERNÁNDEZ, QUIEN SOLICITA MANGUERA NEUTRAL O AISLAR PARA PONERLE A LAS LINEAS DEL POSTE DE LUZ QUE ATRAVIESA LA AZOTEA DE SU CASA. | H84: ING. FRANCISCO | I84: ALTO | J84: 46119 | K84: SI | L84: SDE-UC-00307-26 | M84: AEEH/DG/312/2026, DE FECHA 10/04/2026, ENVIADO AL ING. OCTAVIO GÓMEZ PAULIN COORDINADOR DE GESTIÓN INSTITUCIONAL AEEH/DG/354/2026, DE FECHA 21/04/2026, ENVIADO AL ING. OCTAVIO GÓMEZ PAULIN COORDINADOR DE GESTIÓN INSTITUCIONAL | N84: SI | O84: AEEH/DG/0731/2026, DE FECHA 03/08/2026, ENVIADO AL ING. HUGO ALEJANDRO ABUNDIS GONZÁLEZ, SUPERINTENDENTE DE LA COMISIÓN FEDERAL DE ELECTRICIDAD | P84: NO | Q84: N/A | R84: N/A | S84: N/A | T84: N/A | U84: N/A | V84: CIUDADANO (A) | W84: ATENCIÓN AL PUEBLO | X84: 13.- REUBICACIÓN DE POSTES | Y84: 68 TIANGUISTENGO | Z84: TECHIMAL | AA84: FEMENINO | AB84: 8110657579 | AC84: andreagonzalez46960@gmail.com | AD84: 1 | AE84: =AF84/4 -> 1 | AF84: 4 | AG84: GOLFO CENTRO | AH84: ZONA HUEJUTLA
A85: 83 | B85: 289 | C85: ABRIL | D85: 46119 | E85: SEDECO/CGI/TI/0406/2026 SDPEE/DGAP/1823/2026 | F85: AEEH-2*1S.1/01-2026 ASESORIAS EN MATERIA ENERGÉTICA (VARIOS MUNICIPIOS) | G85: ATENDER AL DELEGADO VICENTE CALLEJAS ZAMUDIO, QUIEN SOLICITA EL MEJORAMIENTO DE LA RED DE ENERGIA YA QUE EL VOLTAJE NO ES SUFICIENTE. | H85: ING. FRANCISCO | I85: ALTO | J85: 46119 | K85: SI | L85: SDE-UC-00318-26 | M85: AEEH/DG/313/2026, DE FECHA 10/04/2026, ENVIADO AL ING. OCTAVIO GÓMEZ PAULIN COORDINADOR DE GESTIÓN INSTITUCIONAL. | N85: SI | O85: AEEH/DG/385/2026, DE FECHA 28/04/2026, ENVIADO AL ING. ALEJANDRO YUSULMAN HERNÁNDEZ LEAL, SUPERINTENDENTE DE CFE DISTRIBUCIÓN ZONA IXMIQUILPAN. | P85: NO | Q85: N/A | R85: N/A | S85: N/A | T85: N/A | U85: N/A | V85: DELEGADO (A) MUNICIPAL | W85: ATENCIÓN AL PUEBLO | X85: 8.- MEJORAS A LA RED | Y85: 6 ALFAJAYUCAN | Z85: XOTHE | AA85: MASCULINO | AB85: 77121367168 | AD85: 1 | AE85: =AF85/4 -> 50 | AF85: 200 | AG85: DIVISION BAJIO | AH85: ZONA IXMIQUILPAN
A86: 84 | B86: 288 | C86: ABRIL | D86: 46119 | E86: SEDECO/CGI/TI/0405/2026 SDPEE/DGAP/1818/2026 | F86: AEEH-2*1S.1/01-2026 ASESORIAS EN MATERIA ENERGÉTICA (VARIOS MUNICIPIOS) | G86: ATENDER A OMAR RAMIREZ SAN JUAN, QUIEN SOLICITA ELECTRIFICACIÓN EN CAMINO RURAL DE SU LOCALIDAD | H86: ING. FRANCISCO | I86: ALTO | J86: 46119 | K86: SI | L86: SDE-UC-00317-26 | M86: AEEH/DG/314/2026, DE FECHA 10/04/2026, ENVIADO AL ING. OCTAVIO GÓMEZ PAULIN COORDINADOR DE GESTIÓN INSTITUCIONAL AEEH/DG/353/2026, DE FECHA 21/04/2026, ENVIADO AL ING. OCTAVIO GÓMEZ PAULIN COORDINADOR DE GESTIÓN INSTITUCIONAL | N86: NO | O86: N/A | P86: N/A | Q86: N/A | R86: N/A | S86: N/A | T86: N/A | U86: N/A | V86: CIUDADANO (A) | W86: ATENCIÓN AL PUEBLO | X86: 3.- ELECTRIFICACIÓN | Y86: 58 TASQUILLO | Z86: CANDHO | AA86: MASCULINO | AB86: 7721165773 | AD86: 1 | AE86: =AF86/4 -> 5 | AF86: 20 | AG86: DIVISION BAJIO | AH86: ZONA IXMIQUILPAN
A87: 85 | B87: 286 | C87: ABRIL | D87: 46119 | E87: SEDECO/CGI/TI/0403/2026 SDPEE/DGAP/1773/2026 | F87: AEEH-2*1S.1/01-2026 ASESORIAS EN MATERIA ENERGÉTICA (VARIOS MUNICIPIOS) | G87: ATENDER A LA C. ÁNGELA GARCÍA ORTÍZ, QUIEN SOLICITA APOYO PARA LA ILUMINACIÓN DEL BOULEVARD UBICADO EN LA ENTRADA DE SU MUNICIPIO | H87: ING. FRANCISCO | I87: ALTO | J87: 46119 | K87: SI | L87: SDE-UC-00310-26 | M87: AEEH/DG/315/2026, DE FECHA 10/04/2026, ENVIADO AL ING. OCTAVIO GÓMEZ PAULIN COORDINADOR DE GESTIÓN INSTITUCIONAL AEEH/DG/366/2026, DE FECHA 21/04/2026, ENVIADO AL ING. OCTAVIO GÓMEZ PAULIN COORDINADOR DE GESTIÓN INSTITUCIONAL | N87: NO | O87: N/A | P87: N/A | Q87: N/A | R87: N/A | S87: N/A | T87: N/A | U87: N/A | V87: CIUDADANO (A) | W87: ATENCIÓN AL PUEBLO | X87: 2.- ALUMBRADO PÚBLICO | Y87: 44 NOPALA DE VILLAGRÁN | Z87: COL. LA PRESA | AA87: FEMENINO | AB87: 5534881345 | AD87: 1 | AE87: =AF87/4 -> 270 | AF87: 1080 | AG87: DIVISION BAJIO | AH87: ZONA IXMIQUILPAN
A88: 86 | B88: 290 | C88: ABRIL | D88: 46119 | E88: SEDECO/CGI/TI/0407/2026 SDPEE/DGAP/1806/2026 | F88: AEEH-2*1S.1/01-2026 ASESORIAS EN MATERIA ENERGÉTICA (VARIOS MUNICIPIOS) | G88: ATENDER A ARTURO OLGUIN NICOLAS, QUIEN SOLICITA 20 LAMPARAS PARA LA CALLE MORELOS. | H88: ING. FRANCISCO | I88: ALTO | J88: 46119 | K88: SI | L88: SDE-UC-00313-26 | M88: AEEH/DG/316/2026, DE FECHA 10/04/2026, ENVIADO AL ING. OCTAVIO GÓMEZ PAULIN COORDINADOR DE GESTIÓN INSTITUCIONAL. | N88: NO | O88: N/A | P88: N/A | Q88: N/A | R88: SI | S88: AEEH/DG/390/2026, DE FECHA 28/04/2026, ENVIADO AL ING. JULIO AGUSTÍN CRUZ TOVAR, PRESIDENTE MUNICIPAL CONSTITUCIONAL DE ALFAJACUYAN. | T88: NO | U88: N/A | V88: CIUDADANO (A) | W88: ATENCIÓN AL PUEBLO | X88: 1.- ADEUDO | Y88: 6 ALFAJAYUCAN | Z88: ZOZEA | AA88: MASCULINO | AB88: 7712055444 | AD88: 1 | AE88: =AF88/4 -> 25 | AF88: 100 | AG88: DIVISION BAJIO | AH88: ZONA IXMIQUILPAN
A89: 87 | B89: 296 | C89: ABRIL | D89: 46119 | E89: SEDECO/CGI/TI/0419/2026 SDPEE/DGAP/1922/2026 | F89: AEEH-2*1S.1/01-2026 ASESORIAS EN MATERIA ENERGÉTICA (VARIOS MUNICIPIOS) | G89: ATENDER A RENÉ GARCÍA MATÍAS, QUIEN SOLICITA ENERGIA ELECTRICA PARA SU COMUNIDAD | H89: ING. FRANCISCO | I89: ALTO | J89: 46119 | K89: SI | L89: SDE-UC-00360-26 | M89: AEEH/DG/317/2026, DE FECHA 10/04/2026, ENVIADO AL ING. OCTAVIO GÓMEZ PAULIN COORDINADOR DE GESTIÓN INSTITUCIONAL AEEH/DG/355/2026, DE FECHA 21/04/2026, ENVIADO AL ING. OCTAVIO GÓMEZ PAULIN COORDINADOR DE GESTIÓN INSTITUCIONAL | N89: SI | O89: AEEH/DG/0731/2026, DE FECHA 03/08/2026, ENVIADO AL ING. HUGO ALEJANDRO ABUNDIS GONZÁLEZ | P89: NO | Q89: N/A | R89: N/A | S89: N/A | T89: N/A | U89: N/A | V89: CIUDADANO (A) | W89: ATENCIÓN AL PUEBLO | X89: 8.- MEJORAS A LA RED | Y89: 53 SAN BARTOLO TUTOTEPEC | Z89: EL JOVIÓN | AA89: MASCULINO | AB89: 7298249350 | AD89: 1 | AE89: =AF89/4 -> 1 | AF89: 4 | AG89: GOLFO CENTRO | AH89: ZONA HUEJUTLA
A90: 88 | B90: 287 | C90: ABRIL | D90: 46119 | E90: SEDECO/CGI/TI/0404/2026 SDPEE/DGAP/1808/2026 | F90: AEEH-2*1S.1/01-2026 ASESORIAS EN MATERIA ENERGÉTICA (VARIOS MUNICIPIOS) | G90: ATENDER A LA DELEGADA DALILA MARIO LOPEZ, QUIEN SOLICITA LA AMPLIACIÓN DE RED ELECTRICA Y LA REUBICACIÓN DE POSTES | H90: ING. FRANCISCO | I90: ALTO | J90: 46119 | K90: SI | L90: SDE-UC-00315-26 | M90: AEEH/DG/318/2026, DE FECHA 10/04/2026, ENVIADO AL ING. OCTAVIO GÓMEZ PAULIN COORDINADOR DE GESTIÓN INSTITUCIONAL | N90: NO | O90: N/A | P90: N/A | Q90: N/A | R90: N/A | S90: N/A | T90: N/A | U90: N/A | V90: DELEGADO (A) MUNICIPAL | W90: ATENCIÓN AL PUEBLO | X90: 3.- ELECTRIFICACIÓN | Y90: 6 ALFAJAYUCAN | Z90: ZOZEA | AA90: FEMENINO | AB90: 7721124999 | AD90: 1 | AE90: =AF90/4 -> 20 | AF90: 80 | AG90: DIVISION BAJIO | AH90: ZONA IXMIQUILPAN
A91: 89 | B91: 076 | C91: FEBRERO | D91: 46057 | E91: SDPEE/0044/2026 SEDECO/CGI/TI/0107/2026 | F91: AEEH-2*1S.5/01-2026 ENERGIA REGIONAL | G91: BRINDAR ATENCIÓN AL DIRECTOR DE PROYECTOS DE ENERGÍA REGIONAL, QUIEN DESEA PRESENTAR UN PROYECTO DE ELECTRICIDAD | H91: ARQ. ORLANDO | I91: ALTO | J91: 46057 | K91: SI | L91: SDE-UCC-07705-26 | M91: AEEH/DG/319/2026, DE FECHA 10/04/2026, ENVIADO AL ING. OCTAVIO GOMEZ PAULIN, COORDINADOR DE GESTÍON INSTITUCIONAL ARQ. ORLANDO SE CONECTA A LA REUNIÓN CON EL C. MIGUEL ÁNGEL HORTA MARTIN | N91: N/A | O91: N/A | P91: N/A | Q91: N/A | R91: N/A | S91: N/A | T91: N/A | U91: N/A | V91: EMPRESA PRIVADA | W91: OTRAS INSTANCIAS | X91: 7.- INVITACIONES/EXPOS/CONGRESOS/TEMAS ADMINISTRATIVOS/CAPACITACIONES/ATENCIÓN A EMPRESAS/ELECTROMOVILIDAD/OTROS | AA91: MASCULINO | AB91: 55 41 77 30 76 | AC91: miguel.horta@eregional.com.mx | AD91: 1 | AE91: 1 | AF91: 0 | AG91: N/A | AH91: N/A
A92: 90 | B92: 265 | C92: MARZO | D92: 46111 | E92: CEDSPI/DGAPI/082/2026 | F92: AEEH-2*1S.5/03-2026 FOTEASE SFV BOMBEOS | G92: INFORMAR EL ESTAUS DEL OFICIO CEDSPI/DC/428/2025, DONDE EL COMISIONADO ESTATAL PARA EL DESARROLLO SOSTENIBLE DE LOS PUEBLOS INDIGENAS, SOLICITA DATOS PARA EJECUTAR RECURSOS EN "TRANSICION ENERGETICA" DEL FOTEASE | H92: ARQ. DIEGO | I92: ALTO | J92: 46111 | K92: SI | L92: SDE-AEEH-00271-25 | M92: AEEH/DG/321/2026, DE FECHA 13/04/2026, ENVIADO A LA MTRA. LUZ ELENA GONZALEZ ESCOBAR DE LA SECRETARÍA DE ENERGÍA (SENER) AEEH/DG/467/2026, DE FECHA 26/05/2026, ENVIADO AL ING. ANDRÉS RIVERA ROSALES, DIRECTOR GENERAL DE ATENCIÓN A PUEBLOS INDÍGENAS DE LA COMISIÓN ESTATAL PARA EL DESARROLLO SOSTENIBLE DE LOS PUEBLOS INDÍGENAS | N92: N/A | O92: N/A | P92: N/A | Q92: N/A | R92: N/A | S92: N/A | T92: N/A | U92: N/A | V92: DEPENDENCIA ESTATAL | W92: OTRAS INSTANCIAS | X92: 7.- INVITACIONES/EXPOS/CONGRESOS/TEMAS ADMINISTRATIVOS/CAPACITACIONES/ATENCIÓN A EMPRESAS/ELECTROMOVILIDAD/OTROS | AA92: MASCULINO | AB92: 771 473 7073 | AD92: 1 | AE92: 1 | AF92: 0 | AG92: N/A | AH92: N/A
A93: 91 | B93: 313 | C93: ABRIL | D93: 46125 | E93: SEDECO/CGI/TI/0444/2026 SDPEE/DGAP/2146/2026 | F93: AEEH-2*1S.1/01-2026 ASESORIAS EN MATERIA ENERGÉTICA (VARIOS MUNICIPIOS) | G93: ATENDER A TANIA YADIRA RAMÍREZ FUENTES, QUIEN SOLICITA LA AMPLIACIÓN DE RED ELECTRICA Y 10 LAMPARAS DE ALUMBRADO PUBLICO | H93: ING. FRANCISCO | I93: ALTO | J93: 46125 | K93: SI | L93: SDE-UC-00398-26 | M93: AEEH/DG/356/2026, DE FECHA 21/04/2026, ENVIADO AL ING. OCTAVIO GOMEZ PAULIN, COORDINADOR DE GESTIÓN INSTITUCIONAL | N93: N/A | O93: N/A | P93: N/A | Q93: N/A | R93: N/A | S93: N/A | T93: N/A | U93: N/A | V93: DELEGADO (A) MUNICIPAL | W93: ATENCIÓN AL PUEBLO | X93: 3.- ELECTRIFICACIÓN | Y93: 29 HUICHAPAN | Z93: ZAMORANO | AA93: FEMENINO | AB93: 5534414165 | AD93: 1 | AE93: =AF93/4 -> 30 | AF93: 120 | AG93: DIVISION BAJIO | AH93: ZONA IXMIQUILPAN
A94: 92 | B94: 314 | C94: ABRIL | D94: 46125 | E94: SEDECO/CGI/TI/0445/2026 SDPEE/DGAP/2159/2026 | F94: AEEH-2*1S.1/01-2026 ASESORIAS EN MATERIA ENERGÉTICA (VARIOS MUNICIPIOS) | G94: ATENDER A ELOÍSA GONZÁLEZ GONZÁLEZ, QUIEN SOLICITA 10 POSTES PARA AMPLIACION DE RED ELCECTRICA Y ALUMBRADO PUBLICO | H94: ING. FRANCISCO | I94: ALTO | J94: 46125 | K94: SI | L94: SDE-UC-00399-26 | M94: AEEH/DG/357/2026, DE FECHA 21/04/2026, ENVIADO AL ING. OCTAVIO GÓMEZ PAULIN | N94: SI | O94: AEEH/DG/433/2026, DE FECHA 14/05/2026, ENVIADO AL ING. ALEJANDRO YUSULMAN HERNÁNDEZ LEAL, SUPERINTENDENTE DE LA CFE ZONA IXMIQUILPAN | P94: NO | Q94: N/A | R94: N/A | S94: N/A | T94: N/A | U94: N/A | V94: DELEGADO (A) MUNICIPAL | W94: ATENCIÓN AL PUEBLO | X94: 2.- ALUMBRADO PÚBLICO | Y94: 29 HUICHAPAN | AA94: FEMENINO | AB94: 7731549928 | AC94: elivago@live.com.mx | AD94: 1 | AE94: =AF94/4 -> 29 | AF94: 116 | AG94: DIVISION BAJIO | AH94: ZONA IXMIQUILPAN
A95: 93 | B95: 315 | C95: ABRIL | D95: 46125 | E95: SEDECO/CGI/TI/0449/2026 SDPEE/DGAP/2197/2026 | F95: AEEH-2*1S.1/01-2026 ASESORIAS EN MATERIA ENERGÉTICA (VARIOS MUNICIPIOS) | G95: ATENDER A PEDRO GUERRERO GONZALEZ, QUIEN SOLICITA LA AMPLIACIÓN DE LA RED DE ENERGIA ELECTRICA Y COLOCACIÓN DE 2 TRANSFORMADORES EN SU LOCALIDAD | H95: ING. FRANCISCO | I95: ALTO | J95: 46125 | K95: SI | L95: SDE-UC-00405-26 | M95: AEEH/DG/358/2026, DE FECHA 21/04/2026, ENVIADO AL ING. OCTAVIO GOMEZ PAULIN | N95: NO | O95: N/A | P95: N/A | Q95: N/A | R95: N/A | S95: N/A | T95: N/A | U95: N/A | V95: DELEGADO (A) MUNICIPAL | W95: ATENCIÓN AL PUEBLO | X95: 8.- MEJORAS A LA RED | Y95: 29 HUICHAPAN | Z95: JONACOPA | AA95: MASCULINO | AB95: 7731284313 | AC95: pedroguerrerogonz30@gmail.com | AD95: 1 | AE95: =AF95/4 -> 30 | AF95: 120 | AG95: DIVISION BAJIO | AH95: ZONA IXMIQUILPAN
A96: 94 | B96: 300 | C96: ABRIL | D96: 46125 | E96: SEDECO/CGI/TI/0425/2026 SDPEE/DGAP/1971/2026 | F96: AEEH-2*1S.1/01-2026 ASESORIAS EN MATERIA ENERGÉTICA (VARIOS MUNICIPIOS) | G96: ATENDER A CAMILO PIÑA BENITEZ, QUIEN SOLICITA EL MEJORAMIENTO DE ALUMBRADO PUBLICO EN SU LOCALIDAD | H96: ING. FRANCISCO | I96: ALTO | J96: 46125 | K96: SI | L96: SDE-UC-00361-206 | M96: AEEH/DG/360/2026, DE FECHA 21/04/206, ENVIADO AL ING. OCTAVIO GOMEZ PAULIN | N96: N/A | O96: N/A | P96: N/A | Q96: N/A | R96: N/A | S96: N/A | T96: N/A | U96: N/A | V96: DELEGADO (A) MUNICIPAL | W96: ATENCIÓN AL PUEBLO | X96: 2.- ALUMBRADO PÚBLICO | Y96: 17 CHAPANTONGO | Z96: TLAUNILOLPAN | AA96: MASCULINO | AB96: 6144471640 | AD96: 1 | AE96: =AF96/4 -> 2 | AF96: 8 | AG96: CENTRO ORIENTE | AH96: ZONA TULA
A97: 95 | B97: 309 | C97: ABRIL | D97: 46125 | E97: SEDECO/CGI/TI/0438/2026 SDPEE/DGAP/2084/2026 | F97: AEEH-2*1S.1/01-2026 ASESORIAS EN MATERIA ENERGÉTICA (VARIOS MUNICIPIOS) | G97: ATENDER A ARMANDO ROMERO DIAZ, QUIEN SOLICITA 10 LAMPARAS DE ALUBRADO PUBLICO EN SU LOCALIDAD | H97: ING. FRANCISCO | I97: ALTO | J97: 46125 | K97: SI | L97: SDE-UC-00371-26 | M97: AEEH/DG/361/2026, DE FECHA 21/04/2026, ENVIADO AL ING. OCTAVIO GOMEZ PAULIN | N97: N/A | O97: N/A | P97: N/A | Q97: N/A | R97: SI | S97: AEEH/DG/454/2026, DE FECHA 20/05/2026, ENVIADO A LA MTRA. YEYMI YADIRA SOLÍS ZAVALA | T97: N/A | U97: N/A | V97: DELEGADO (A) MUNICIPAL | W97: ATENCIÓN AL PUEBLO | X97: 2.- ALUMBRADO PÚBLICO | Y97: 29 HUICHAPAN | Z97: TLAXCALILLA | AA97: MASCULINO | AB97: 4272243984 | AD97: 1 | AE97: =AF97/4 -> 20 | AF97: 80 | AG97: DIVISION BAJIO | AH97: ZONA IXMIQUILPAN
A98: 96 | B98: 307 | C98: ABRIL | D98: 46125 | E98: SEDECO/CGI/TI/0436/2026 SDPEE/DGAP/2074/2026 | F98: AEEH-2*1S.1/01-2026 ASESORIAS EN MATERIA ENERGÉTICA (VARIOS MUNICIPIOS) | G98: ATENDER A ARMANDO ROMERO DIAZ, QUIEN SOLICITA 3 POSTES PARA LA AMPLIACIÓN DE RED ELECTRICA | H98: ING. FRANCISCO | I98: ALTO | J98: 46125 | K98: SI | L98: SDE-UC-00370-26 | M98: AEEH/DG/362/2026, DE FECHA 21/04/2026, ENVIADO AL ING.OCTAVIO GOMEZ PAULIN AEEH/DG/507/2026, DE FECHA 05/06/2026, ENVIADO AL ING.OCTAVIO GOMEZ PAULIN | N98: NO | O98: N/A | P98: N/A | Q98: N/A | R98: N/A | S98: N/A | T98: N/A | U98: N/A | V98: DELEGADO (A) MUNICIPAL | W98: ATENCIÓN AL PUEBLO | X98: 3.- ELECTRIFICACIÓN | Y98: 29 HUICHAPAN | Z98: TLAXCALILLA | AA98: MASCULINO | AB98: 4272243984 | AD98: 1 | AE98: =AF98/4 -> 20 | AF98: 80 | AG98: DIVISION BAJIO | AH98: ZONA IXMIQUILPAN
A99: 97 | B99: 308 | C99: ABRIL | D99: 46125 | E99: SEDECO/CGI/TI/0437/2026 SDPEE/DGAP/2078/2026 | F99: AEEH-2*1S.1/01-2026 ASESORIAS EN MATERIA ENERGÉTICA (VARIOS MUNICIPIOS) | G99: ATENDER A RICARDO TREJO SALVADOR, QUIEN SOLICITA ALUMBRADO PÚBLICO EN SU LOCALIDAD | H99: ING. FRANCISCO | I99: ALTO | J99: 46125 | K99: SI | L99: SDE-UC-00447-26 | M99: AEEH/DG/364/2026, DE FECHA 21/04/2026, ENVIADO AL ING OCTAVIO GOMEZ PAULIN | N99: N/A | O99: N/A | P99: N/A | Q99: N/A | R99: N/A | S99: N/A | T99: N/A | U99: N/A | V99: DELEGADO (A) MUNICIPAL | W99: ATENCIÓN AL PUEBLO | X99: 2.- ALUMBRADO PÚBLICO | Y99: 29 HUICHAPAN | Z99: LA ESTACION | AA99: MASCULINO | AB99: 7731470996 | AD99: 1 | AE99: =AF99/4 -> 20 | AF99: 80 | AG99: DIVISION BAJIO | AH99: ZONA IXMIQUILPAN
A100: 98 | B100: 303 | C100: ABRIL | D100: 46125 | E100: SEDECO/CGI/TI/0428/2026 SDPEE/DGAP/2052/2026 | F100: AEEH-2*1S.1/01-2026 ASESORIAS EN MATERIA ENERGÉTICA (VARIOS MUNICIPIOS) | G100: ATENDER A BERNARDA LETICIA GALVÁN SÁNCHEZ, QUIEN SOLICITA LA HABILITACIÓN DE UN TRANSFOMADOR Y ALUMBRADO PÚBLICO EN SU LOCALIDAD | H100: ING. FRANCISCO | I100: ALTO | J100: 46125 | K100: SI | L100: SDE-UC-00365-26 | M100: AEEH/DG/365/2026, DE FECHA 21/04/2026, ENVIADO AL ING. OCTAVIO GOMEZ PAULIN | N100: N/A | O100: N/A | P100: N/A | Q100: N/A | R100: N/A | S100: N/A | T100: N/A | U100: N/A | V100: DELEGADO (A) MUNICIPAL | W100: ATENCIÓN AL PUEBLO | X100: 2.- ALUMBRADO PÚBLICO | Y100: 17 CHAPANTONGO | Z100: SAN ANTONIO | AA100: FEMENINO | AB100: 7721048497 | AC100: ulises9santiagos@gmail.com | AD100: 1 | AE100: =AF100/4 -> 42 | AF100: 168 | AG100: CENTRO ORIENTE | AH100: ZONA TULA
...

Sheet Clasificaciones
A1: RESPONSABLE DE DAR ATENCIÓN | B1: No. DE SOLICITUDES | D1: ¿SOLICITUD ATENDIDA? | E1: NO. DE OFICIO | G1: SOLICITUD INGRESADA POR | H1: TOTAL DE SOLICITUDES | J1: ATENCIÓN AL PUEBLO | K1: TOTAL DE SOLICITUDES | M1: CLASIFICACIONES DE SOLICITUDES DE LA AEEH | N1: No. | P1: MUNICIPIOS TOTALES | Q1: MUNICIPIOS CON SOLICITUD | R1: MUNICIPIOS SIN SOLICITUD | T1: MUNICIPIO | U1: TOTAL DE SOLICITUDES POR MUNICIPIO | W1: Mes de solicitud | X1: Total de solicitudes | Z1: beneficiarios indirectos | AA1: Total de beneficiarios por mes | AC1: GÉNERO | AD1: TOTAL DE SOLICITUDES
A2: ARQ. ORLANDO | B2: =COUNTIF('Correspondencia AEEH 2026'!$H$3:$H$1048576,Clasificaciones!A2) -> 38 | D2: SI | E2: =COUNTIF('Correspondencia AEEH 2026'!$K$3:$K$1048576,Clasificaciones!D2) -> 282 | G2: AYUNTAMIENTO | H2: =COUNTIF('Correspondencia AEEH 2026'!$K$3:$V$1048576,Clasificaciones!G2) -> 8 | J2: SI | K2: =COUNTIF('Correspondencia AEEH 2026'!$W$3:$W$1048576,Clasificaciones!J2) -> 0 | M2: 1.- ADEUDO | N2: =COUNTIF('Correspondencia AEEH 2026'!$X$3:$X$1048576,Clasificaciones!M2) -> 8 | P2: =COUNTA(T2:T87) -> 84 | Q2: =COUNTIF(T2:U87, ">0") -> 62 | R2: =COUNTIF(T2:U87, 0) -> 22 | T2: 1 ACATLÁN | U2: =COUNTIF('Correspondencia AEEH 2026'!$Y$3:$Y$1048576,Clasificaciones!T2) -> 0 | W2: ENERO | X2: =COUNTIF('Correspondencia AEEH 2026'!$C$3:$C$1048576,Clasificaciones!W2) -> 6 | Z2: ENERO | AA2: =SUMIF('Correspondencia AEEH 2026'!C:C,Clasificaciones!Z2,'Correspondencia AEEH 2026'!AF:AF) -> 708 | AC2: MASCULINO | AD2: =COUNTIF('Correspondencia AEEH 2026'!$AA$3:$AA$1048576,Clasificaciones!AC2) -> 123
A3: ARQ. ORLANDO ING. FRANCISCO | B3: =COUNTIF('Correspondencia AEEH 2026'!$H$3:$H$1048576,Clasificaciones!A3) -> 0 | D3: NO | E3: =COUNTIF('Correspondencia AEEH 2026'!$K$3:$K$1048576,Clasificaciones!D3) -> 0 | G3: CIUDADANO (A) | H3: =COUNTIF('Correspondencia AEEH 2026'!$K$3:$V$1048576,Clasificaciones!G3) -> 128 | J3: NO | K3: =COUNTIF('Correspondencia AEEH 2026'!$W$3:$W$1048576,Clasificaciones!J3) -> 0 | M3: 2.- ALUMBRADO PÚBLICO | N3: =COUNTIF('Correspondencia AEEH 2026'!$X$3:$X$1048576,Clasificaciones!M3) -> 47 | T3: 2 ACAXOCHITLÁN | U3: =COUNTIF('Correspondencia AEEH 2026'!$Y$3:$Y$1048576,Clasificaciones!T3) -> 4 | W3: FEBRERO | X3: =COUNTIF('Correspondencia AEEH 2026'!$C$3:$C$1048576,Clasificaciones!W3) -> 42 | Z3: FEBRERO | AA3: =SUMIF('Correspondencia AEEH 2026'!C:C,Clasificaciones!Z3,'Correspondencia AEEH 2026'!AF:AF) -> 2767 | AC3: FEMENINO | AD3: =COUNTIF('Correspondencia AEEH 2026'!$AA$3:$AA$1048576,Clasificaciones!AC3) -> 63
A4: ING. FRANCISCO | B4: =COUNTIF('Correspondencia AEEH 2026'!$H$3:$H$1048576,Clasificaciones!A4) -> 123 | D4: EN PROCESO | E4: =COUNTIF('Correspondencia AEEH 2026'!$K$3:$K$1048576,Clasificaciones!D4) -> 15 | G4: DELEGADO (A) MUNICIPAL | H4: =COUNTIF('Correspondencia AEEH 2026'!$K$3:$V$1048576,Clasificaciones!G4) -> 28 | J4: TOTAL | K4: =SUM(K2:K3) -> 0 | M4: 3.- ELECTRIFICACIÓN | N4: =COUNTIF('Correspondencia AEEH 2026'!$X$3:$X$1048576,Clasificaciones!M4) -> 58 | T4: 3 ACTOPAN | U4: =COUNTIF('Correspondencia AEEH 2026'!$Y$3:$Y$1048576,Clasificaciones!T4) -> 1 | W4: MARZO | X4: =COUNTIF('Correspondencia AEEH 2026'!$C$3:$C$1048576,Clasificaciones!W4) -> 37 | Z4: MARZO | AA4: =SUMIF('Correspondencia AEEH 2026'!C:C,Clasificaciones!Z4,'Correspondencia AEEH 2026'!AF:AF) -> 4624 | AC4: MASCULINO | AD4: =COUNTIF('Correspondencia AEEH 2026'!$AA$3:$AA$1048576,Clasificaciones!AC4) -> 123
A5: ARQ. ORLANDO ARQ. DIEGO | B5: =COUNTIF('Correspondencia AEEH 2026'!$H$3:$H$1048576,Clasificaciones!A5) -> 8 | D5: TOTAL | E5: =SUM(E2:E4) -> 297 | G5: DEPENDENCIA ESTATAL | H5: =COUNTIF('Correspondencia AEEH 2026'!$K$3:$V$1048576,Clasificaciones!G5) -> 72 | M5: 4.- ENERGÍA RENOVABLE (SOLAR, EÓLICA) | N5: =COUNTIF('Correspondencia AEEH 2026'!$X$3:$X$1048576,Clasificaciones!M5) -> 9 | T5: 4 AGUA BLANCA DE ITURBIDE | U5: =COUNTIF('Correspondencia AEEH 2026'!$Y$3:$Y$1048576,Clasificaciones!T5) -> 1 | W5: ABRIL | X5: =COUNTIF('Correspondencia AEEH 2026'!$C$3:$C$1048576,Clasificaciones!W5) -> 37 | Z5: ABRIL | AA5: =SUMIF('Correspondencia AEEH 2026'!C:C,Clasificaciones!Z5,'Correspondencia AEEH 2026'!AF:AF) -> 2696 | AC5: TOTAL | AD5: =SUM(AD3:AD4) -> 186
A6: ARQ. DIEGO | B6: =COUNTIF('Correspondencia AEEH 2026'!$H$3:$H$1048576,Clasificaciones!A6) -> 54 | G6: DEPENDENCIA FEDERAL | H6: =COUNTIF('Correspondencia AEEH 2026'!$K$3:$V$1048576,Clasificaciones!G6) -> 49 | M6: 5.- HIDROCARBUROS | N6: =COUNTIF('Correspondencia AEEH 2026'!$X$3:$X$1048576,Clasificaciones!M6) -> 0 | T6: 5 AJACUBA | U6: =COUNTIF('Correspondencia AEEH 2026'!$Y$3:$Y$1048576,Clasificaciones!T6) -> 4 | W6: MAYO | X6: =COUNTIF('Correspondencia AEEH 2026'!$C$3:$C$1048576,Clasificaciones!W6) -> 36 | Z6: MAYO | AA6: =SUMIF('Correspondencia AEEH 2026'!C:C,Clasificaciones!Z6,'Correspondencia AEEH 2026'!AF:AF) -> 2434
A7: ARQ. ORLANDO ING. FRANCISCO ARQ. DIEGO | B7: =COUNTIF('Correspondencia AEEH 2026'!$H$3:$H$1048576,Clasificaciones!A7) -> 0 | G7: EMPRESA PRIVADA | H7: =COUNTIF('Correspondencia AEEH 2026'!$K$3:$V$1048576,Clasificaciones!G7) -> 7 | M7: 6.- INFRAESTRUCTURA ELÉCTRICA | N7: =COUNTIF('Correspondencia AEEH 2026'!$X$3:$X$1048576,Clasificaciones!M7) -> 5 | T7: 6 ALFAJAYUCAN | U7: =COUNTIF('Correspondencia AEEH 2026'!$Y$3:$Y$1048576,Clasificaciones!T7) -> 4 | W7: JUNIO | X7: =COUNTIF('Correspondencia AEEH 2026'!$C$3:$C$1048576,Clasificaciones!W7) -> 45 | Z7: JUNIO | AA7: =SUMIF('Correspondencia AEEH 2026'!C:C,Clasificaciones!Z7,'Correspondencia AEEH 2026'!AF:AF) -> 0
A8: ING. FRANCISCO ARQ. DIEGO | B8: =COUNTIF('Correspondencia AEEH 2026'!$H$3:$H$1048576,Clasificaciones!A8) -> 0 | G8: INSTITUCIÓN EDUCATIVA | H8: =COUNTIF('Correspondencia AEEH 2026'!$K$3:$V$1048576,Clasificaciones!G8) -> 0 | M8: 7.- INVITACIONES/EXPOS/CONGRESOS/TEMAS ADMINISTRATIVOS/CAPACITACIONES/ATENCIÓN A EMPRESAS/ELECTROMOVILIDAD/OTROS | N8: =COUNTIF('Correspondencia AEEH 2026'!$X$3:$X$1048576,Clasificaciones!M8) -> 100 | T8: 7 ALMOLOYA | U8: =COUNTIF('Correspondencia AEEH 2026'!$Y$3:$Y$1048576,Clasificaciones!T8) -> 2 | W8: JULIO | X8: =COUNTIF('Correspondencia AEEH 2026'!$C$3:$C$1048576,Clasificaciones!W8) -> 31 | Z8: JULIO | AA8: =SUMIF('Correspondencia AEEH 2026'!C:C,Clasificaciones!Z8,'Correspondencia AEEH 2026'!AF:AF) -> 1
A9: ING. SANDRA | B9: =COUNTIF('Correspondencia AEEH 2026'!$H$3:$H$1048576,Clasificaciones!A9) -> 45 | G9: TOTAL | H9: =SUM(H2:H8) -> 292 | M9: 8.- MEJORAS A LA RED | N9: =COUNTIF('Correspondencia AEEH 2026'!$X$3:$X$1048576,Clasificaciones!M9) -> 25 | T9: 8 APAN | U9: =COUNTIF('Correspondencia AEEH 2026'!$Y$3:$Y$1048576,Clasificaciones!T9) -> 2 | W9: AGOSTO | X9: =COUNTIF('Correspondencia AEEH 2026'!$C$3:$C$1048576,Clasificaciones!W9) -> 51 | Z9: AGOSTO | AA9: =SUMIF('Correspondencia AEEH 2026'!C:C,Clasificaciones!Z9,'Correspondencia AEEH 2026'!AF:AF) -> 0
A10: LIC. ARELI | B10: =COUNTIF('Correspondencia AEEH 2026'!$H$3:$H$1048576,Clasificaciones!A10) -> 14 | M10: 9.- SISTEMAS DE BOMBEO DE AGUA POTABLE | N10: =COUNTIF('Correspondencia AEEH 2026'!$X$3:$X$1048576,Clasificaciones!M10) -> 0 | T10: 9 EL ARENAL | U10: =COUNTIF('Correspondencia AEEH 2026'!$Y$3:$Y$1048576,Clasificaciones!T10) -> 3 | W10: SEPTIEMBRE | X10: =COUNTIF('Correspondencia AEEH 2026'!$C$3:$C$1048576,Clasificaciones!W10) -> 12 | Z10: SEPTIEMBRE | AA10: =SUMIF('Correspondencia AEEH 2026'!C:C,Clasificaciones!Z10,'Correspondencia AEEH 2026'!AF:AF) -> 0
A11: LIC. ARELI ING. FRANCISCO | B11: =COUNTIF('Correspondencia AEEH 2026'!$H$3:$H$1048576,Clasificaciones!A11) -> 2 | M11: 10.- SISTEMAS DE BOMBEO PARA RIEGO AGRICOLA | N11: =COUNTIF('Correspondencia AEEH 2026'!$X$3:$X$1048576,Clasificaciones!M11) -> 0 | T11: 10 ATITALAQUIA | U11: =COUNTIF('Correspondencia AEEH 2026'!$Y$3:$Y$1048576,Clasificaciones!T11) -> 0 | W11: OCTUBRE | X11: =COUNTIF('Correspondencia AEEH 2026'!$C$3:$C$1048576,Clasificaciones!W11) -> 0 | Z11: OCTUBRE | AA11: =SUMIF('Correspondencia AEEH 2026'!C:C,Clasificaciones!Z11,'Correspondencia AEEH 2026'!AF:AF) -> 0
A12: ING. FRANCISCO ING. SANDRA | B12: =COUNTIF('Correspondencia AEEH 2026'!$H$3:$H$1048576,Clasificaciones!A12) -> 0 | M12: 11.- TELECOMUNICACIONES | N12: =COUNTIF('Correspondencia AEEH 2026'!$X$3:$X$1048576,Clasificaciones!M12) -> 2 | T12: 11 ATLAPEXCO | U12: =COUNTIF('Correspondencia AEEH 2026'!$Y$3:$Y$1048576,Clasificaciones!T12) -> 2 | W12: NOVIEMBRE | X12: =COUNTIF('Correspondencia AEEH 2026'!$C$3:$C$1048576,Clasificaciones!W12) -> 0 | Z12: NOVIEMBRE | AA12: =SUMIF('Correspondencia AEEH 2026'!C:C,Clasificaciones!Z12,'Correspondencia AEEH 2026'!AF:AF) -> 0
A13: ARQ. ORLANDO ING. SANDRA | B13: =COUNTIF('Correspondencia AEEH 2026'!$H$3:$H$1048576,Clasificaciones!A13) -> 6 | M13: 12.- SEGUIMIENTO A SOLICITUDES | N13: =COUNTIF('Correspondencia AEEH 2026'!$X$3:$X$1048576,Clasificaciones!M13) -> 33 | T13: 12 ATOTONILCO EL GRANDE | U13: =COUNTIF('Correspondencia AEEH 2026'!$Y$3:$Y$1048576,Clasificaciones!T13) -> 2 | W13: DICIEMBRE | X13: =COUNTIF('Correspondencia AEEH 2026'!$C$3:$C$1048576,Clasificaciones!W13) -> 0 | Z13: DICIEMBRE | AA13: =SUMIF('Correspondencia AEEH 2026'!C:C,Clasificaciones!Z13,'Correspondencia AEEH 2026'!AF:AF) -> 0
A14: ARQ. DIEGO ING. SANDRA | B14: =COUNTIF('Correspondencia AEEH 2026'!$H$3:$H$1048576,Clasificaciones!A14) -> 1 | M14: 13.- REUBICACIÓN DE POSTES | N14: =COUNTIF('Correspondencia AEEH 2026'!$X$3:$X$1048576,Clasificaciones!M14) -> 9 | T14: 13 ATOTONILCO DE TULA | U14: =COUNTIF('Correspondencia AEEH 2026'!$Y$3:$Y$1048576,Clasificaciones!T14) -> 1
A15: LIC. ARELI ING. SANDRA | B15: =COUNTIF('Correspondencia AEEH 2026'!$H$3:$H$1048576,Clasificaciones!A15) -> 1 | M15: 14.- CONCILIACIÓN ANTE CFE | N15: =COUNTIF('Correspondencia AEEH 2026'!$X$3:$X$1048576,Clasificaciones!M15) -> 1 | T15: 14 CALNALI | U15: =COUNTIF('Correspondencia AEEH 2026'!$Y$3:$Y$1048576,Clasificaciones!T15) -> 5
A16: ARQ. ORLANDO LIC. ARELI | B16: =COUNTIF('Correspondencia AEEH 2026'!$H$3:$H$1048576,Clasificaciones!A16) -> 2 | M16: TOTAL | N16: =SUM(N2:N14) -> 296 | T16: 15 CARDONAL | U16: =COUNTIF('Correspondencia AEEH 2026'!$Y$3:$Y$1048576,Clasificaciones!T16) -> 1
A17: ARQ. ORLANDO LIC. ARELI ING. SANDRA ARQ. DIEGO | B17: =COUNTIF('Correspondencia AEEH 2026'!$H$3:$H$1048576,Clasificaciones!A17) -> 2
A18: ARQ. ORLANDO ING. SANDRA ARQ. DIEGO | B18: =COUNTIF('Correspondencia AEEH 2026'!$H$3:$H$1048576,Clasificaciones!A18) -> 1
A19: TOTAL | B19: =SUM(B2:B16) -> 294 | T19: 16 CUAUTEPEC DE HINOJOSA | U19: =COUNTIF('Correspondencia AEEH 2026'!$Y$3:$Y$1048576,Clasificaciones!T19) -> 10 | W19: TOTAL | X19: =SUM(X2:X13) -> 297 | Z19: TOTALES | AA19: =SUM(AA2:AA13) -> 13230
T20: 17 CHAPANTONGO | U20: =COUNTIF('Correspondencia AEEH 2026'!$Y$3:$Y$1048576,Clasificaciones!T20) -> 4
T21: 18 CHAPULHUACÁN | U21: =COUNTIF('Correspondencia AEEH 2026'!$Y$3:$Y$1048576,Clasificaciones!T21) -> 3
T22: 19 CHILCUAUTLA | U22: =COUNTIF('Correspondencia AEEH 2026'!$Y$3:$Y$1048576,Clasificaciones!T22) -> 3
T23: 20 ELOXOCHITLÁN | U23: =COUNTIF('Correspondencia AEEH 2026'!$Y$3:$Y$1048576,Clasificaciones!T23) -> 1 | W23: Etiquetas de fila | X23: Cuenta de TIPO DE SOLICITUD
T24: 21 EMILIANO ZAPATA | U24: =COUNTIF('Correspondencia AEEH 2026'!$Y$3:$Y$1048576,Clasificaciones!T24) -> 1 | W24: SI | X24: 199
T25: 22 EPAZOYUCAN | U25: =COUNTIF('Correspondencia AEEH 2026'!$Y$3:$Y$1048576,Clasificaciones!T25) -> 2 | W25: 1 ELECTRIFICACIÓN | X25: 66
T26: 23 FRANCISCO I. MADERO | U26: =COUNTIF('Correspondencia AEEH 2026'!$Y$3:$Y$1048576,Clasificaciones!T26) -> 1 | W26: 10 SISTEMA FOTOVOLTAICO AISLADO | X26: 1
T27: 24 HUASCA DE OCAMPO | U27: =COUNTIF('Correspondencia AEEH 2026'!$Y$3:$Y$1048576,Clasificaciones!T27) -> 1 | W27: 11 ALTOS COSTOS Y ADEUDOS | X27: 14
T28: 25 HUAUTLA | U28: =COUNTIF('Correspondencia AEEH 2026'!$Y$3:$Y$1048576,Clasificaciones!T28) -> 5 | W28: 12 REUBICACIÓN DE POSTE | X28: 21
T29: 26 HUAZALINGO | U29: =COUNTIF('Correspondencia AEEH 2026'!$Y$3:$Y$1048576,Clasificaciones!T29) -> 0 | W29: 13 RIEGO AGRICOLA | X29: 2
T30: 27 HUEHUETLA | U30: =COUNTIF('Correspondencia AEEH 2026'!$Y$3:$Y$1048576,Clasificaciones!T30) -> 0 | W30: 14 ADMTVO./PERSONAL | X30: 1
T31: 28 HUEJUTLA DE REYES | U31: =COUNTIF('Correspondencia AEEH 2026'!$Y$3:$Y$1048576,Clasificaciones!T31) -> 3 | W31: 2 ALUMBRADO PÚBLICO | X31: 26
T32: 29 HUICHAPAN | U32: =COUNTIF('Correspondencia AEEH 2026'!$Y$3:$Y$1048576,Clasificaciones!T32) -> 10 | W32: 3 TELECOMUNICACIONES | X32: 10
T33: 30 IXMIQUILPAN | U33: =COUNTIF('Correspondencia AEEH 2026'!$Y$3:$Y$1048576,Clasificaciones!T33) -> 2 | W33: 5 EFICIENCIA ENERGÉTICA | X33: 1
T34: 31 JACALA DE LEDEZMA | U34: =COUNTIF('Correspondencia AEEH 2026'!$Y$3:$Y$1048576,Clasificaciones!T34) -> 1 | W34: 6 ENERGÍAS RENOVABLES | X34: 5
T35: 32 JALTOCÁN | U35: =COUNTIF('Correspondencia AEEH 2026'!$Y$3:$Y$1048576,Clasificaciones!T35) -> 0 | W35: 7 INFRAESTRUCTURA ELÉCTRICA | X35: 13
... T38: 35 METEPEC | U38: =COUNTIF('Correspondencia AEEH 2026'!$Y$3:$Y$1048576,Clasificaciones!T38) -> 3 | W38: Total general | X38: 199
T39: 36 SAN AGUSTÍN METZQUITITLÁN | U39: =COUNTIF('Correspondencia AEEH 2026'!$Y$3:$Y$1048576,Clasificaciones!T39) -> 0
T40: 37 METZTITLÁN | U40: =COUNTIF('Correspondencia AEEH 2026'!$Y$3:$Y$1048576,Clasificaciones!T40) -> 2
T41: 38 MINERAL DEL CHICO | U41: =COUNTIF('Correspondencia AEEH 2026'!$Y$3:$Y$1048576,Clasificaciones!T41) -> 1
T42: 39 MINERAL DEL MONTE | U42: =COUNTIF('Correspondencia AEEH 2026'!$Y$3:$Y$1048576,Clasificaciones!T42) -> 0
T43: 40 LA MISIÓN | U43: =COUNTIF('Correspondencia AEEH 2026'!$Y$3:$Y$1048576,Clasificaciones!T43) -> 0
T44: 41 MIXQUIAHUALA DE JUÁREZ | U44: =COUNTIF('Correspondencia AEEH 2026'!$Y$3:$Y$1048576,Clasificaciones!T44) -> 1
T45: 42 MOLANGO DE ESCAMILLA | U45: =COUNTIF('Correspondencia AEEH 2026'!$Y$3:$Y$1048576,Clasificaciones!T45) -> 1
T46: 43 NICOLÁS FLORES | U46: =COUNTIF('Correspondencia AEEH 2026'!$Y$3:$Y$1048576,Clasificaciones!T46) -> 0
T47: 44 NOPALA DE VILLAGRÁN | U47: =COUNTIF('Correspondencia AEEH 2026'!$Y$3:$Y$1048576,Clasificaciones!T47) -> 1
T48: 45 OMITLÁN DE JUÁREZ | U48: =COUNTIF('Correspondencia AEEH 2026'!$Y$3:$Y$1048576,Clasificaciones!T48) -> 4
T49: 46 SAN FELIPE ORIZATLÁN | U49: =COUNTIF('Correspondencia AEEH 2026'!$Y$3:$Y$1048576,Clasificaciones!T49) -> 0
T50: 47 PACULA | U50: =COUNTIF('Correspondencia AEEH 2026'!$Y$3:$Y$1048576,Clasificaciones!T50) -> 1
... T87: 84 ZIMAPÁN | U87: =COUNTIF('Correspondencia AEEH 2026'!$Y$3:$Y$1048576,Clasificaciones!T87) -> 0
T88: TOTAL | U88: =SUM(U2:U87) -> 169

Sheet INDICADORES
A2: MES | B2: (Todas) | D2: Oficios Ingresados | E2: Atención al Pueblo | G2: Otras Instancias (Federales, Estatales y Municipales) | I2: Seguimiento a solicitudes | L2: Clasificación Total de Correspondencia | O2: No. De solicitudes
E3: Solicitudes Atendidas | F3: Solicitudes en Proceso | G3: Solicitudes Atendidas | H3: Solicitudes en Proceso | L3: 1.- ADEUDO | O3: =Clasificaciones!N2 -> 8 | V3: Municipios con solicitudes | W3: Municipios Hgo | X3: Municipios con solicitud | Y3: Municipios sin solicitud | AB3: Mes de atención | AC3: Número de mujeres directas atendidas | AD3: Número de hombres directos atendidos
A4: Etiquetas de fila | D4: =GETPIVOTDATA("No. DE TURNO",$A$2) -> #REF! | E4: =GETPIVOTDATA("No. DE TURNO",$A$2,"¿SOLICITUD ATENDIDA?","SI","ÁREA GENERADORA ","ATENCIÓN AL PUEBLO") -> #REF! | F4: =GETPIVOTDATA("No. DE TURNO",$A$2,"¿SOLICITUD ATENDIDA?","EN PROCESO","ÁREA GENERADORA ","ATENCIÓN AL PUEBLO") -> #REF! | G4: =GETPIVOTDATA("No. DE TURNO",$A$2,"¿SOLICITUD ATENDIDA?","SI","ÁREA GENERADORA ","OTRAS INSTANCIAS") -> #REF! | H4: 0 | I4: =GETPIVOTDATA("No. DE TURNO",$A$2,"ÁREA GENERADORA ","SEGUIMIENTO A SOLICITUDES") -> #REF! | L4: 2.- ALUMBRADO PÚBLICO | O4: =Clasificaciones!N3 -> 47 | W4: =Clasificaciones!P2 -> 84 | X4: =Clasificaciones!Q2 -> 62 | Y4: =Clasificaciones!R2 -> 22 | AB4: ENERO | AC4: =GETPIVOTDATA("PERSONAS ATENDIDAS",$AB$19,"MES","ENERO","GÉNERO ","FEMENINO ") -> 3 | AD4: =GETPIVOTDATA("PERSONAS ATENDIDAS",$AB$19,"MES","ENERO","GÉNERO ","MASCULINO ") -> 3
A5: ATENCIÓN AL PUEBLO | L5: 3.- ELECTRIFICACIÓN | O5: =Clasificaciones!N4 -> 58 | AB5: FEBRERO | AC5: =GETPIVOTDATA("PERSONAS ATENDIDAS",$AB$19,"MES","FEBRERO","GÉNERO ","FEMENINO ") -> 9 | AD5: =GETPIVOTDATA("PERSONAS ATENDIDAS",$AB$19,"MES","FEBRERO","GÉNERO ","MASCULINO ") -> 23
A6: SI | L6: 4.- ENERGÍA RENOVABLE (SOLAR, EÓLICA) | O6: =Clasificaciones!N5 -> 9 | AB6: MARZO | AC6: =GETPIVOTDATA("PERSONAS ATENDIDAS",$AB$19,"MES","MARZO","GÉNERO ","FEMENINO ") -> 13 | AD6: =GETPIVOTDATA("PERSONAS ATENDIDAS",$AB$19,"MES","MARZO","GÉNERO ","MASCULINO ") -> 22
A7: OTRAS INSTANCIAS | L7: 5.- HIDROCARBUROS | O7: =Clasificaciones!N6 -> 0 | AB7: ABRIL | AC7: =GETPIVOTDATA("PERSONAS ATENDIDAS",$AB$19,"MES","ABRIL","GÉNERO ","FEMENINO ") -> 9 | AD7: =GETPIVOTDATA("PERSONAS ATENDIDAS",$AB$19,"MES","ABRIL","GÉNERO ","MASCULINO ") -> 15
A8: SI | L8: 6.- INFRAESTRUCTURA ELÉCTRICA | O8: =Clasificaciones!N7 -> 5 | AB8: MAYO | AC8: =GETPIVOTDATA("PERSONAS ATENDIDAS",$AB$19,"MES","MAYO","GÉNERO ","FEMENINO ") -> 4 | AD8: =GETPIVOTDATA("PERSONAS ATENDIDAS",$AB$19,"MES","MAYO","GÉNERO ","MASCULINO ") -> 10
A9: SEGUIMIENTO A SOLICITUDES | L9: 7.- INVITACIONES/EXPOS/CONGRESOS/TEMAS ADMINISTRATIVOS/CAPACITACIONES/ATENCIÓN A EMPRESAS/ELECTROMOVILIDAD/OTROS | O9: =Clasificaciones!N8 -> 100 | AB9: JUNIO | AC9: =Clasificaciones!AU8 -> 0 | AD9: =Clasificaciones!AV8 -> 0
A10: SI | L10: 8.- MEJORAS A LA RED | O10: =Clasificaciones!N9 -> 25 | AB10: JULIO | AC10: =Clasificaciones!AU9 -> 0 | AD10: =Clasificaciones!AV9 -> 0
A11: (en blanco) | L11: 9.- SISTEMAS DE BOMBEO DE AGUA POTABLE | O11: =Clasificaciones!N10 -> 0 | AB11: AGOSTO | AC11: =Clasificaciones!AU10 -> 0 | AD11: =Clasificaciones!AV10 -> 0
A12: SI | L12: 10.- SISTEMAS DE BOMBEO PARA RIEGO AGRICOLA | O12: =Clasificaciones!N11 -> 0 | AB12: SEPTIEMBRE | AC12: =Clasificaciones!AU11 -> 0 | AD12: =Clasificaciones!AV11 -> 0
A13: Total general | L13: 11.- TELECOMUNICACIONES | O13: =Clasificaciones!N12 -> 2 | AB13: OCTUBRE | AC13: =Clasificaciones!AU12 -> 0 | AD13: =Clasificaciones!AV12 -> 0
L14: 12.- SEGUIMIENTO A SOLICITUDES | O14: =Clasificaciones!N13 -> 33 | AB14: NOVIEMBRE | AC14: =Clasificaciones!AU13 -> 0 | AD14: =Clasificaciones!AV13 -> 0
L15: 13.- REUBICACIÓN DE POSTES | O15: =Clasificaciones!N14 -> 9 | AB15: DICIEMBRE | AC15: =Clasificaciones!AU19 -> 0 | AD15: =Clasificaciones!AV19 -> 0
L16: TOTAL | O16: =SUM(O3:O15) -> 296 | AB16: TOTALES | AC16: =SUM(AC4:AC15) -> 38 | AD16: =SUM(AD4:AD15) -> 73
R17: ÁREA GENERADORA | S17: ATENCIÓN AL PUEBLO
L18: Clasificación de Correspondencia turnada por la Dirección de Atención al Pueblo | O18: No. De solicitudes | R18: MES | S18: (Todas)
L19: 1.- ADEUDO | O19: =GETPIVOTDATA("No. DE TURNO",$R$20,"CLASIFICACIÓN ","1.- ADEUDO ") -> #REF! | AB19: Suma de Personas Atendidas | AC19: Etiquetas de columna
L20: 2.- ALUMBRADO PÚBLICO | O20: =GETPIVOTDATA("No. DE TURNO",$R$20,"CLASIFICACIÓN ","2.- ALUMBRADO PÚBLICO") -> #REF! | R20: Etiquetas de fila | AB20: Etiquetas de fila | AC20: FEMENINO | AD20: MASCULINO | AE20: (en blanco) | AF20: Total general
L21: 3.- ELECTRIFICACIÓN | O21: =GETPIVOTDATA("No. DE TURNO",$R$20,"CLASIFICACIÓN ","3.- ELECTRIFICACIÓN") -> #REF! | R21: 1.- ADEUDO | AB21: ENERO | AC21: 3 | AD21: 3 | AF21: 6
L22: 4.- ENERGÍA RENOVABLE (SOLAR, EÓLICA) | O22: =GETPIVOTDATA("No. DE TURNO",$R$20,"CLASIFICACIÓN ","4.- ENERGÍA RENOVABLE (SOLAR, EÓLICA)") -> #REF! | R22: 2.- ALUMBRADO PÚBLICO | AB22: FEBRERO | AC22: 9 | AD22: 23 | AE22: 0 | AF22: 32
L23: 6.- INFRAESTRUCTURA ELÉCTRICA | O23: =GETPIVOTDATA("No. DE TURNO",$R$20,"CLASIFICACIÓN ","6.- INFRAESTRUCTURA ELÉCTRICA") -> #REF! | R23: 7.- INVITACIONES/EXPOS/CONGRESOS/TEMAS ADMINISTRATIVOS/CAPACITACIONES/ATENCIÓN A EMPRESAS/ELECTROMOVILIDAD/OTROS | AB23: MARZO | AC23: 13 | AD23: 22 | AE23: 2 | AF23: 37
L24: 7.- INVITACIONES/EXPOS/CONGRESOS/TEMAS ADMINISTRATIVOS/CAPACITACIONES/ATENCIÓN A EMPRESAS/ELECTROMOVILIDAD/OTROS | O24: =GETPIVOTDATA("No. DE TURNO",$R$20,"CLASIFICACIÓN ","7.- INVITACIONES/EXPOS/CONGRESOS/TEMAS ADMINISTRATIVOS/CAPACITACIONES/ATENCIÓN A EMPRESAS/ELECTROMOVILIDAD/OTROS ") -> #REF! | R24: 8.- MEJORAS A LA RED | AB24: ABRIL | AC24: 9 | AD24: 15 | AE24: 1 | AF24: 25
L25: 8.- MEJORAS A LA RED | O25: =GETPIVOTDATA("No. DE TURNO",$R$20,"CLASIFICACIÓN ","8.- MEJORAS A LA RED") -> #REF! | R25: 3.- ELECTRIFICACIÓN | AB25: MAYO | AC25: 4 | AD25: 10 | AE25: 6 | AF25: 20
L26: 13.- REUBICACIÓN DE POSTES | O26: =GETPIVOTDATA("No. DE TURNO",$R$20,"CLASIFICACIÓN ","13.- REUBICACIÓN DE POSTES ") -> #REF! | R26: 4.- ENERGÍA RENOVABLE (SOLAR, EÓLICA) | V26: Municipio | W26: Total de Solicitudes por Municipio | AB26: (en blanco)
L27: TOTAL | O27: =SUM(O19:O26) -> #REF! | R27: 6.- INFRAESTRUCTURA ELÉCTRICA | V27: 2 ACAXOCHITLÁN | W27: 4 | AB27: Total general | AC27: 38 | AD27: 73 | AE27: 9 | AF27: 120
R28: 13.- REUBICACIÓN DE POSTES | V28: 3 ACTOPAN | W28: 1
R29: 14.- CONCILIACIÓN ANTE CFE | V29: 4 AGUA BLANCA DE ITURBIDE | W29: 1
R30: Total general | V30: 6 ALFAJAYUCAN | W30: 4 | AB30: Mes de atención | AC30: Número de mujeres indirectas atendidas | AD30: Número de hombres indirectos atendidos
R31: ÁREA GENERADORA | S31: OTRAS INSTANCIAS | V31: 8 APAN | W31: 1 | AB31: ENERO | AC31: =GETPIVOTDATA("Beneficiarios Indirectos",$AB$45,"MES","ENERO","GÉNERO ","FEMENINO ") -> 604 | AD31: =GETPIVOTDATA("Beneficiarios Indirectos",$AB$45,"MES","ENERO","GÉNERO ","MASCULINO ") -> 104
L32: Clasificación de Correspondencia turnada por Otras Instancias (Federales, Estatales y Municipales) | O32: No. De solicitudes | R32: MES | S32: (Todas) | V32: 9 EL ARENAL | W32: 2 | AB32: FEBRERO | AC32: =GETPIVOTDATA("Beneficiarios Indirectos",$AB$45,"MES","FEBRERO","GÉNERO ","FEMENINO ") -> 355 | AD32: =GETPIVOTDATA("Beneficiarios Indirectos",$AB$45,"MES","FEBRERO","GÉNERO ","MASCULINO ") -> 2412
L33: 2.- ALUMBRADO PÚBLICO | O33: =GETPIVOTDATA("No. DE TURNO",$R$34,"CLASIFICACIÓN ","2.- ALUMBRADO PÚBLICO") -> #REF! | V33: 11 ATLAPEXCO | W33: 2 | AB33: MARZO | AC33: =GETPIVOTDATA("Beneficiarios Indirectos",$AB$45,"MES","MARZO","GÉNERO ","FEMENINO ") -> 402 | AD33: =GETPIVOTDATA("Beneficiarios Indirectos",$AB$45,"MES","MARZO","GÉNERO ","MASCULINO ") -> 4222
L34: 3.- ELECTRIFICACIÓN | O34: =GETPIVOTDATA("No. DE TURNO",$R$34,"CLASIFICACIÓN ","3.- ELECTRIFICACIÓN") -> #REF! | R34: Etiquetas de fila | V34: 12 ATOTONILCO EL GRANDE | W34: 2 | AB34: ABRIL | AC34: =GETPIVOTDATA("Beneficiarios Indirectos",$AB$45,"MES","ABRIL","GÉNERO ","FEMENINO ") -> 1692 | AD34: =GETPIVOTDATA("Beneficiarios Indirectos",$AB$45,"MES","ABRIL","GÉNERO ","MASCULINO ") -> 1004
L35: 7.- INVITACIONES/EXPOS/CONGRESOS/TEMAS ADMINISTRATIVOS/CAPACITACIONES/ATENCIÓN A EMPRESAS/ELECTROMOVILIDAD/OTROS | O35: =GETPIVOTDATA("No. DE TURNO",$R$34,"CLASIFICACIÓN ","7.- INVITACIONES/EXPOS/CONGRESOS/TEMAS ADMINISTRATIVOS/CAPACITACIONES/ATENCIÓN A EMPRESAS/ELECTROMOVILIDAD/OTROS ") -> #REF! | R35: 2.- ALUMBRADO PÚBLICO | V35: 13 ATOTONILCO DE TULA | W35: 1 | AB35: MAYO | AC35: =GETPIVOTDATA("Beneficiarios Indirectos",$AB$45,"MES","MAYO","GÉNERO ","FEMENINO ") -> 4 | AD35: =GETPIVOTDATA("Beneficiarios Indirectos",$AB$45,"MES","MAYO","GÉNERO ","MASCULINO ") -> 2430
L36: TOTAL | O36: =SUM(O33:O35) -> #REF! | R36: 7.- INVITACIONES/EXPOS/CONGRESOS/TEMAS ADMINISTRATIVOS/CAPACITACIONES/ATENCIÓN A EMPRESAS/ELECTROMOVILIDAD/OTROS | V36: 14 CALNALI | W36: 2 | AB36: JUNIO | AC36: =Clasificaciones!AU37 -> 0 | AD36: =Clasificaciones!AV37 -> 0
R37: Total general | V37: 17 CHAPANTONGO | W37: 4 | AB37: JULIO | AC37: =Clasificaciones!AU38 -> 0 | AD37: =Clasificaciones!AV38 -> 0
V38: 18 CHAPULHUACÁN | W38: 1 | AB38: AGOSTO | AC38: =Clasificaciones!AU39 -> 0 | AD38: =Clasificaciones!AV39 -> 0
V39: 20 ELOXOCHITLÁN | W39: 1 | AB39: SEPTIEMBRE | AC39: =Clasificaciones!AU40 -> 0 | AD39: =Clasificaciones!AV40 -> 0
V40: 22 EPAZOYUCAN | W40: 2 | AB40: OCTUBRE | AC40: =Clasificaciones!AU41 -> 0 | AD40: =Clasificaciones!AV41 -> 0
R41: MES | S41: (Todas) | V41: 24 HUASCA DE OCAMPO | W41: 1 | AB41: NOVIEMBRE | AC41: =Clasificaciones!AU42 -> 0 | AD41: =Clasificaciones!AV42 -> 0
V42: 26 HUAZALINGO | W42: 1 | AB42: DICIEMBRE | AC42: =Clasificaciones!AU43 -> 0 | AD42: =Clasificaciones!AV43 -> 0
L43: Clasificación Total de Correspondencia Gestionada ante CFE | O43: No. De solicitudes | R43: Etiquetas de fila | V43: 28 HUEJUTLA DE REYES | W43: 4 | AB43: TOTALES | AC43: =SUM(AC31:AC42) -> 3057 | AD43: =SUM(AD31:AD42) -> 10172
L44: 1.- ADEUDO | O44: =GETPIVOTDATA("No. DE TURNO",$R$43,"¿SOLICITUD GESTIONADA ANTE CFE?","SI","CLASIFICACIÓN ","1.- ADEUDO ") -> #REF! | R44: SI | V44: 29 HUICHAPAN | W44: 10
L45: 2.- ALUMBRADO PÚBLICO | O45: =GETPIVOTDATA("No. DE TURNO",$R$43,"¿SOLICITUD GESTIONADA ANTE CFE?","SI","CLASIFICACIÓN ","2.- ALUMBRADO PÚBLICO") -> #REF! | R45: 1.- ADEUDO | V45: 35 METEPEC | W45: 3 | AB45: Suma de Beneficiarios Indirectos | AC45: Etiquetas de columna
L46: 3.- ELECTRIFICACIÓN | O46: =GETPIVOTDATA("No. DE TURNO",$R$43,"¿SOLICITUD GESTIONADA ANTE CFE?","SI","CLASIFICACIÓN ","3.- ELECTRIFICACIÓN") -> #REF! | R46: 2.- ALUMBRADO PÚBLICO | V46: 44 NOPALA DE VILLAGRÁN | W46: 1 | AB46: Etiquetas de fila | AC46: FEMENINO | AD46: MASCULINO | AE46: (en blanco) | AF46: Total general
L47: 7.- INVITACIONES/EXPOS/CONGRESOS/TEMAS ADMINISTRATIVOS/CAPACITACIONES/ATENCIÓN A EMPRESAS/ELECTROMOVILIDAD/OTROS | O47: =GETPIVOTDATA("No. DE TURNO",$R$43,"¿SOLICITUD GESTIONADA ANTE CFE?","SI","CLASIFICACIÓN ","7.- INVITACIONES/EXPOS/CONGRESOS/TEMAS ADMINISTRATIVOS/CAPACITACIONES/ATENCIÓN A EMPRESAS/ELECTROMOVILIDAD/OTROS ") -> #REF! | R47: 8.- MEJORAS A LA RED | V47: 45 OMITLÁN DE JUÁREZ | W47: 4 | AB47: ENERO | AC47: 604 | AD47: 104 | AF47: 708
L48: 8.- MEJORAS A LA RED | O48: =GETPIVOTDATA("No. DE TURNO",$R$43,"¿SOLICITUD GESTIONADA ANTE CFE?","SI","CLASIFICACIÓN ","8.- MEJORAS A LA RED") -> #REF! | R48: 3.- ELECTRIFICACIÓN | V48: 47 PACULA | W48: 1 | AB48: FEBRERO | AC48: 355 | AD48: 2412 | AE48: 0 | AF48: 2767
L49: 13.- REUBICACIÓN DE POSTES | O49: =GETPIVOTDATA("No. DE TURNO",$R$43,"¿SOLICITUD GESTIONADA ANTE CFE?","SI","CLASIFICACIÓN ","13.- REUBICACIÓN DE POSTES ") -> #REF! | R49: 4.- ENERGÍA RENOVABLE (SOLAR, EÓLICA) | V49: 48 PACHUCA DE SOTO | W49: 23 | AB49: MARZO | AC49: 402 | AD49: 4222 | AE49: 0 | AF49: 4624
L50: TOTAL | O50: =SUM(O44:O49) -> #REF! | R50: 6.- INFRAESTRUCTURA ELÉCTRICA | V50: 52 SAN AGUSTÍN TLAXIACA | W50: 3 | AB50: ABRIL | AC50: 1692 | AD50: 1004 | AE50: 0 | AF50: 2696
R51: 13.- REUBICACIÓN DE POSTES | V51: 53 SAN BARTOLO TUTOTEPEC | W51: 1 | AB51: MAYO | AC51: 4 | AD51: 2430 | AE51: 0 | AF51: 2434
R52: MES | S52: (Todas) | V52: 56 SANTIAGO TULANTEPEC DE LUGO GUERRERO | W52: 1 | AB52: (en blanco)
V53: 57 SINGUILUCAN | W53: 1 | AB53: Total general | AC53: 3057 | AD53: 10172 | AE53: 0 | AF53: 13229
L54: Clasificación Total de Correspondencia Atendida por CFE | O54: No. De solicitudes | R54: Etiquetas de fila | S54: Cuenta de No. DE TURNO | V54: 58 TASQUILLO | W54: 2
L55: 1.- ADEUDO | O55: =GETPIVOTDATA("No. DE TURNO",$R$54,"¿CFE DIO RESPUESTA?","SI","CLASIFICACIÓN ","1.- ADEUDO ") -> 1 | R55: SI | S55: 8 | V55: 61 TEPEAPULCO | W55: 4
L56: 3.- ELECTRIFICACIÓN | O56: =GETPIVOTDATA("No. DE TURNO",$R$54,"¿CFE DIO RESPUESTA?","SI","CLASIFICACIÓN ","3.- ELECTRIFICACIÓN") -> 4 | R56: 1.- ADEUDO | S56: 1 | V56: 62 TEPEHUACÁN DE GUERRERO | W56: 1
L57: 7.- INVITACIONES/EXPOS/CONGRESOS/TEMAS ADMINISTRATIVOS/CAPACITACIONES/ATENCIÓN A EMPRESAS/ELECTROMOVILIDAD/OTROS | O57: =GETPIVOTDATA("No. DE TURNO",$R$43,"¿SOLICITUD GESTIONADA ANTE CFE?","SI","CLASIFICACIÓN ","7.- INVITACIONES/EXPOS/CONGRESOS/TEMAS ADMINISTRATIVOS/CAPACITACIONES/ATENCIÓN A EMPRESAS/ELECTROMOVILIDAD/OTROS ") -> #REF! | R57: 3.- ELECTRIFICACIÓN | S57: 4 | V57: 67 TEZONTEPEC DE ALDAMA | W57: 1
L58: 8.- MEJORAS A LA RED | O58: =GETPIVOTDATA("No. DE TURNO",$R$54,"¿CFE DIO RESPUESTA?","SI","CLASIFICACIÓN ","8.- MEJORAS A LA RED") -> 2 | R58: 7.- INVITACIONES/EXPOS/CONGRESOS/TEMAS ADMINISTRATIVOS/CAPACITACIONES/ATENCIÓN A EMPRESAS/ELECTROMOVILIDAD/OTROS | S58: 1 | V58: 68 TIANGUISTENGO | W58: 1
L59: TOTAL | O59: =SUM(O55:O58) -> #REF! | R59: 8.- MEJORAS A LA RED | S59: 2 | V59: 72 TLANALAPA | W59: 1
R60: Total general | S60: 8 | V60: 73 TLANCHINOL | W60: 1
V61: 77 TULANCINGO DE BRAVO | W61: 4
V62: 82 ZAPOTLÁN DE JUÁREZ | W62: 1
V63: 83 ZEMPOALA | W63: 8
V64: TOTAL | W64: 106
V65: MES | W65: (Todas)
V67: Etiquetas de fila | W67: Cuenta de No. DE TURNO
V68: 48 PACHUCA DE SOTO | W68: 23
V69: 13.- REUBICACIÓN DE POSTES | W69: 1
V70: 7.- INVITACIONES/EXPOS/CONGRESOS/TEMAS ADMINISTRATIVOS/CAPACITACIONES/ATENCIÓN A EMPRESAS/ELECTROMOVILIDAD/OTROS | W70: 22
V71: Total general | W71: 23

Sheet Formato Correspondencia
A1: CONTROL EXTERNO DE CORRESPONDECIA DPIE 2026
A2: No. de Tarjeta y/o No. oficio | B2: No. de Turno | C2: Fecha de Turno Recepción AEEH | D2: Fecha de Recibido por la DPIE | E2: Vo.Bo. Director | F2: A s u n t o / Peticionario | G2: TURNADO A | H2: NIVEL DE PRIORIDAD | I2: FIRMA Y FECHA DE QUIEN RECIBE
